{
  "steps": [
    {
      "aimPoint": {
        "x": 184.59609985351563,
        "y": 150.0
      },
      "direction": 0.0,
      "dropPoint": {
        "x": 212.85687255859375,
        "y": 224.34115600585938
      },
      "position": {
        "x": 150.0,
        "y": 150.0
      },
      "predictedTarget": {
        "x": 235.1941680908203,
        "y": 250.7595977783203
      },
      "state": "Stopped",
      "targetIndex": 2
    },
    {
      "aimPoint": {
        "x": 184.59609985351563,
        "y": 150.0
      },
      "direction": 0.10000000149011612,
      "dropPoint": {
        "x": 212.855224609375,
        "y": 224.31858825683594
      },
      "position": {
        "x": 150.0,
        "y": 150.0
      },
      "predictedTarget": {
        "x": 235.19613647460938,
        "y": 250.73397827148438
      },
      "state": "Turning",
      "targetIndex": 2
    },
    {
      "aimPoint": {
        "x": 184.42324829101563,
        "y": 153.45384216308594
      },
      "direction": 0.20000000298023224,
      "dropPoint": {
        "x": 212.85357666015625,
        "y": 224.2960205078125
      },
      "position": {
        "x": 150.0,
        "y": 150.0
      },
      "predictedTarget": {
        "x": 235.19810485839844,
        "y": 250.70835876464844
      },
      "state": "Turning",
      "targetIndex": 2
    },
    {
      "aimPoint": {
        "x": 183.90647888183594,
        "y": 156.87318420410156
      },
      "direction": 0.30000001192092896,
      "dropPoint": {
        "x": 212.85191345214844,
        "y": 224.27346801757813
      },
      "position": {
        "x": 150.0,
        "y": 150.0
      },
      "predictedTarget": {
        "x": 235.20005798339844,
        "y": 250.6827392578125
      },
      "state": "Turning",
      "targetIndex": 2
    },
    {
      "aimPoint": {
        "x": 183.0509033203125,
        "y": 160.22384643554688
      },
      "direction": 0.4000000059604645,
      "dropPoint": {
        "x": 212.8502655029297,
        "y": 224.2509002685547
      },
      "position": {
        "x": 150.0,
        "y": 150.0
      },
      "predictedTarget": {
        "x": 235.2020263671875,
        "y": 250.65711975097656
      },
      "state": "Turning",
      "targetIndex": 2
    },
    {
      "aimPoint": {
        "x": 181.8651123046875,
        "y": 163.47235107421875
      },
      "direction": 0.5,
      "dropPoint": {
        "x": 212.84861755371094,
        "y": 224.22833251953125
      },
      "position": {
        "x": 150.0,
        "y": 150.0
      },
      "predictedTarget": {
        "x": 235.20399475097656,
        "y": 250.63148498535156
      },
      "state": "Turning",
      "targetIndex": 2
    },
    {
      "aimPoint": {
        "x": 180.36093139648438,
        "y": 166.58624267578125
      },
      "direction": 0.6000000238418579,
      "dropPoint": {
        "x": 212.84695434570313,
        "y": 224.2057647705078
      },
      "position": {
        "x": 150.0,
        "y": 150.0
      },
      "predictedTarget": {
        "x": 235.20594787597656,
        "y": 250.60586547851563
      },
      "state": "Turning",
      "targetIndex": 2
    },
    {
      "aimPoint": {
        "x": 178.5533905029297,
        "y": 169.534423828125
      },
      "direction": 0.7000000476837158,
      "dropPoint": {
        "x": 212.84530639648438,
        "y": 224.18321228027344
      },
      "position": {
        "x": 150.0,
        "y": 150.0
      },
      "predictedTarget": {
        "x": 235.20791625976563,
        "y": 250.5802459716797
      },
      "state": "Turning",
      "targetIndex": 2
    },
    {
      "aimPoint": {
        "x": 176.46055603027344,
        "y": 172.28741455078125
      },
      "direction": 0.8000000715255737,
      "dropPoint": {
        "x": 212.84365844726563,
        "y": 224.16065979003906
      },
      "position": {
        "x": 150.0,
        "y": 150.0
      },
      "predictedTarget": {
        "x": 235.2098846435547,
        "y": 250.55462646484375
      },
      "state": "Turning",
      "targetIndex": 2
    },
    {
      "aimPoint": {
        "x": 174.10333251953125,
        "y": 174.81771850585938
      },
      "direction": 0.8676772713661194,
      "dropPoint": {
        "x": 212.8419952392578,
        "y": 224.13809204101563
      },
      "position": {
        "x": 150.0,
        "y": 150.0
      },
      "predictedTarget": {
        "x": 235.2118377685547,
        "y": 250.5290069580078
      },
      "state": "Turning",
      "targetIndex": 2
    },
    {
      "aimPoint": {
        "x": 172.36984252929688,
        "y": 176.39089965820313
      },
      "direction": 0.8675400614738464,
      "dropPoint": {
        "x": 212.84034729003906,
        "y": 224.11553955078125
      },
      "position": {
        "x": 150.0,
        "y": 150.0
      },
      "predictedTarget": {
        "x": 235.21380615234375,
        "y": 250.5033721923828
      },
      "state": "Turning",
      "targetIndex": 2
    },
    {
      "aimPoint": {
        "x": 172.3734588623047,
        "y": 176.38783264160156
      },
      "direction": 0.8675400614738464,
      "dropPoint": {
        "x": 212.8386993408203,
        "y": 224.09298706054688
      },
      "position": {
        "x": 150.0,
        "y": 150.0
      },
      "predictedTarget": {
        "x": 235.2157745361328,
        "y": 250.47775268554688
      },
      "state": "Stopped",
      "targetIndex": 2
    },
    {
      "aimPoint": {
        "x": 172.3734588623047,
        "y": 176.38783264160156
      },
      "direction": 0.8672658205032349,
      "dropPoint": {
        "x": 212.8370361328125,
        "y": 224.0704345703125
      },
      "position": {
        "x": 150.01617431640625,
        "y": 150.01905822753906
      },
      "predictedTarget": {
        "x": 235.2177276611328,
        "y": 250.45213317871094
      },
      "state": "Accelerating",
      "targetIndex": 2
    },
    {
      "aimPoint": {
        "x": 172.39686584472656,
        "y": 176.4007568359375
      },
      "direction": 0.8672692775726318,
      "dropPoint": {
        "x": 212.8370819091797,
        "y": 224.0709991455078
      },
      "position": {
        "x": 150.064697265625,
        "y": 150.0762481689453
      },
      "predictedTarget": {
        "x": 235.21768188476563,
        "y": 250.45277404785156
      },
      "state": "Accelerating",
      "targetIndex": 2
    },
    {
      "aimPoint": {
        "x": 172.44529724121094,
        "y": 176.45802307128906
      },
      "direction": 0.8672795295715332,
      "dropPoint": {
        "x": 212.83721923828125,
        "y": 224.07269287109375
      },
      "position": {
        "x": 150.1455535888672,
        "y": 150.17156982421875
      },
      "predictedTarget": {
        "x": 235.21754455566406,
        "y": 250.45469665527344
      },
      "state": "Accelerating",
      "targetIndex": 2
    },
    {
      "aimPoint": {
        "x": 172.52587890625,
        "y": 176.55357360839844
      },
      "direction": 0.8672966957092285,
      "dropPoint": {
        "x": 212.83741760253906,
        "y": 224.07550048828125
      },
      "position": {
        "x": 150.25875854492188,
        "y": 150.30502319335938
      },
      "predictedTarget": {
        "x": 235.21730041503906,
        "y": 250.45790100097656
      },
      "state": "Accelerating",
      "targetIndex": 2
    },
    {
      "aimPoint": {
        "x": 172.63864135742188,
        "y": 176.68740844726563
      },
      "direction": 0.8673208355903625,
      "dropPoint": {
        "x": 212.83770751953125,
        "y": 224.07945251464844
      },
      "position": {
        "x": 150.40431213378906,
        "y": 150.4766082763672
      },
      "predictedTarget": {
        "x": 235.21694946289063,
        "y": 250.46238708496094
      },
      "state": "Accelerating",
      "targetIndex": 2
    },
    {
      "aimPoint": {
        "x": 172.78355407714844,
        "y": 176.8595428466797
      },
      "direction": 0.8673518300056458,
      "dropPoint": {
        "x": 212.83807373046875,
        "y": 224.08450317382813
      },
      "position": {
        "x": 150.5821990966797,
        "y": 150.6863250732422
      },
      "predictedTarget": {
        "x": 235.2165069580078,
        "y": 250.4681396484375
      },
      "state": "Accelerating",
      "targetIndex": 2
    },
    {
      "aimPoint": {
        "x": 172.96063232421875,
        "y": 177.0699462890625
      },
      "direction": 0.8673897981643677,
      "dropPoint": {
        "x": 212.8385467529297,
        "y": 224.09071350097656
      },
      "position": {
        "x": 150.79241943359375,
        "y": 150.93418884277344
      },
      "predictedTarget": {
        "x": 235.21597290039063,
        "y": 250.47518920898438
      },
      "state": "Accelerating",
      "targetIndex": 2
    },
    {
      "aimPoint": {
        "x": 173.1698455810547,
        "y": 177.31866455078125
      },
      "direction": 0.8674348592758179,
      "dropPoint": {
        "x": 212.83909606933594,
        "y": 224.09803771972656
      },
      "position": {
        "x": 151.0349578857422,
        "y": 151.22018432617188
      },
      "predictedTarget": {
        "x": 235.21533203125,
        "y": 250.4835205078125
      },
      "state": "Accelerating",
      "targetIndex": 2
    },
    {
      "aimPoint": {
        "x": 173.41119384765625,
        "y": 177.6056671142578
      },
      "direction": 0.8674868941307068,
      "dropPoint": {
        "x": 212.83973693847656,
        "y": 224.10647583007813
      },
      "position": {
        "x": 151.30982971191406,
        "y": 151.54432678222656
      },
      "predictedTarget": {
        "x": 235.214599609375,
        "y": 250.49313354492188
      },
      "state": "Accelerating",
      "targetIndex": 2
    },
    {
      "aimPoint": {
        "x": 173.6846923828125,
        "y": 177.93096923828125
      },
      "direction": 0.8675461411476135,
      "dropPoint": {
        "x": 212.8404541015625,
        "y": 224.11602783203125
      },
      "position": {
        "x": 151.6170196533203,
        "y": 151.90663146972656
      },
      "predictedTarget": {
        "x": 235.21376037597656,
        "y": 250.50401306152344
      },
      "state": "Accelerating",
      "targetIndex": 2
    },
    {
      "aimPoint": {
        "x": 173.99032592773438,
        "y": 178.2946014404297
      },
      "direction": 0.8676125407218933,
      "dropPoint": {
        "x": 212.84127807617188,
        "y": 224.12673950195313
      },
      "position": {
        "x": 151.95651245117188,
        "y": 152.30709838867188
      },
      "predictedTarget": {
        "x": 235.21282958984375,
        "y": 250.5161895751953
      },
      "state": "Accelerating",
      "targetIndex": 2
    },
    {
      "aimPoint": {
        "x": 174.32806396484375,
        "y": 178.69656372070313
      },
      "direction": 0.8676862716674805,
      "dropPoint": {
        "x": 212.84219360351563,
        "y": 224.13853454589844
      },
      "position": {
        "x": 152.32830810546875,
        "y": 152.7457275390625
      },
      "predictedTarget": {
        "x": 235.2117919921875,
        "y": 250.52964782714844
      },
      "state": "Accelerating",
      "targetIndex": 2
    },
    {
      "aimPoint": {
        "x": 174.69790649414063,
        "y": 179.1368408203125
      },
      "direction": 0.867767333984375,
      "dropPoint": {
        "x": 212.84320068359375,
        "y": 224.15145874023438
      },
      "position": {
        "x": 152.73239135742188,
        "y": 153.2225341796875
      },
      "predictedTarget": {
        "x": 235.21066284179688,
        "y": 250.54437255859375
      },
      "state": "Accelerating",
      "targetIndex": 2
    },
    {
      "aimPoint": {
        "x": 175.099853515625,
        "y": 179.61544799804688
      },
      "direction": 0.8678557872772217,
      "dropPoint": {
        "x": 212.8443145751953,
        "y": 224.16549682617188
      },
      "position": {
        "x": 153.1687469482422,
        "y": 153.73751831054688
      },
      "predictedTarget": {
        "x": 235.20944213867188,
        "y": 250.56039428710938
      },
      "state": "Accelerating",
      "targetIndex": 2
    },
    {
      "aimPoint": {
        "x": 175.53387451171875,
        "y": 180.13241577148438
      },
      "direction": 0.8679518103599548,
      "dropPoint": {
        "x": 212.84552001953125,
        "y": 224.18063354492188
      },
      "position": {
        "x": 153.6373748779297,
        "y": 154.2906951904297
      },
      "predictedTarget": {
        "x": 235.20811462402344,
        "y": 250.5776824951172
      },
      "state": "Accelerating",
      "targetIndex": 2
    },
    {
      "aimPoint": {
        "x": 175.99996948242188,
        "y": 180.687744140625
      },
      "direction": 0.8680555820465088,
      "dropPoint": {
        "x": 212.8468475341797,
        "y": 224.1968994140625
      },
      "position": {
        "x": 154.1382598876953,
        "y": 154.882080078125
      },
      "predictedTarget": {
        "x": 235.20669555664063,
        "y": 250.5962677001953
      },
      "state": "Accelerating",
      "targetIndex": 2
    },
    {
      "aimPoint": {
        "x": 176.49810791015625,
        "y": 181.2814483642578
      },
      "direction": 0.8681670427322388,
      "dropPoint": {
        "x": 212.8482666015625,
        "y": 224.21426391601563
      },
      "position": {
        "x": 154.67140197753906,
        "y": 155.5116729736328
      },
      "predictedTarget": {
        "x": 235.20516967773438,
        "y": 250.61611938476563
      },
      "state": "Accelerating",
      "targetIndex": 2
    },
    {
      "aimPoint": {
        "x": 177.0283203125,
        "y": 181.9135284423828
      },
      "direction": 0.8682866096496582,
      "dropPoint": {
        "x": 212.84979248046875,
        "y": 224.23272705078125
      },
      "position": {
        "x": 155.2367706298828,
        "y": 156.1794891357422
      },
      "predictedTarget": {
        "x": 235.20355224609375,
        "y": 250.6372528076172
      },
      "state": "Accelerating",
      "targetIndex": 2
    },
    {
      "aimPoint": {
        "x": 177.5905303955078,
        "y": 182.58401489257813
      },
      "direction": 0.8684143424034119,
      "dropPoint": {
        "x": 212.8514404296875,
        "y": 224.25228881835938
      },
      "position": {
        "x": 155.8343505859375,
        "y": 156.8855438232422
      },
      "predictedTarget": {
        "x": 235.2018280029297,
        "y": 250.65968322753906
      },
      "state": "Accelerating",
      "targetIndex": 2
    },
    {
      "aimPoint": {
        "x": 178.18472290039063,
        "y": 183.29293823242188
      },
      "direction": 0.868550181388855,
      "dropPoint": {
        "x": 212.8532257080078,
        "y": 224.27294921875
      },
      "position": {
        "x": 156.46414184570313,
        "y": 157.62985229492188
      },
      "predictedTarget": {
        "x": 235.20001220703125,
        "y": 250.68338012695313
      },
      "state": "Accelerating",
      "targetIndex": 2
    },
    {
      "aimPoint": {
        "x": 178.81092834472656,
        "y": 184.040283203125
      },
      "direction": 0.868694543838501,
      "dropPoint": {
        "x": 212.85511779785156,
        "y": 224.29470825195313
      },
      "position": {
        "x": 157.10997009277344,
        "y": 158.39334106445313
      },
      "predictedTarget": {
        "x": 235.19810485839844,
        "y": 250.70835876464844
      },
      "state": "Moving",
      "targetIndex": 2
    },
    {
      "aimPoint": {
        "x": 179.45294189453125,
        "y": 184.80699157714844
      },
      "direction": 0.868694543838501,
      "dropPoint": {
        "x": 212.85511779785156,
        "y": 224.29470825195313
      },
      "position": {
        "x": 157.75579833984375,
        "y": 159.15682983398438
      },
      "predictedTarget": {
        "x": 235.19810485839844,
        "y": 250.70835876464844
      },
      "state": "Moving",
      "targetIndex": 2
    },
    {
      "aimPoint": {
        "x": 180.09878540039063,
        "y": 185.5704803466797
      },
      "direction": 0.868694543838501,
      "dropPoint": {
        "x": 212.85513305664063,
        "y": 224.29470825195313
      },
      "position": {
        "x": 158.40162658691406,
        "y": 159.92031860351563
      },
      "predictedTarget": {
        "x": 235.19810485839844,
        "y": 250.70835876464844
      },
      "state": "Moving",
      "targetIndex": 2
    },
    {
      "aimPoint": {
        "x": 180.74459838867188,
        "y": 186.33396911621094
      },
      "direction": 0.868694543838501,
      "dropPoint": {
        "x": 212.85513305664063,
        "y": 224.29470825195313
      },
      "position": {
        "x": 159.04745483398438,
        "y": 160.68380737304688
      },
      "predictedTarget": {
        "x": 235.19810485839844,
        "y": 250.70835876464844
      },
      "state": "Moving",
      "targetIndex": 2
    },
    {
      "aimPoint": {
        "x": 181.39044189453125,
        "y": 187.0974578857422
      },
      "direction": 0.8686946034431458,
      "dropPoint": {
        "x": 212.85513305664063,
        "y": 224.29470825195313
      },
      "position": {
        "x": 159.6932830810547,
        "y": 161.44729614257813
      },
      "predictedTarget": {
        "x": 235.19810485839844,
        "y": 250.70835876464844
      },
      "state": "Moving",
      "targetIndex": 2
    },
    {
      "aimPoint": {
        "x": 182.0362548828125,
        "y": 187.86094665527344
      },
      "direction": 0.8686946034431458,
      "dropPoint": {
        "x": 212.85513305664063,
        "y": 224.29470825195313
      },
      "position": {
        "x": 160.339111328125,
        "y": 162.21078491210938
      },
      "predictedTarget": {
        "x": 235.19810485839844,
        "y": 250.70835876464844
      },
      "state": "Moving",
      "targetIndex": 2
    },
    {
      "aimPoint": {
        "x": 182.68209838867188,
        "y": 188.6244354248047
      },
      "direction": 0.8686946034431458,
      "dropPoint": {
        "x": 212.85513305664063,
        "y": 224.29470825195313
      },
      "position": {
        "x": 160.9849395751953,
        "y": 162.97427368164063
      },
      "predictedTarget": {
        "x": 235.19810485839844,
        "y": 250.70835876464844
      },
      "state": "Moving",
      "targetIndex": 2
    },
    {
      "aimPoint": {
        "x": 183.32791137695313,
        "y": 189.38792419433594
      },
      "direction": 0.8686946630477905,
      "dropPoint": {
        "x": 212.85513305664063,
        "y": 224.29470825195313
      },
      "position": {
        "x": 161.63076782226563,
        "y": 163.73776245117188
      },
      "predictedTarget": {
        "x": 235.19810485839844,
        "y": 250.70835876464844
      },
      "state": "Moving",
      "targetIndex": 2
    },
    {
      "aimPoint": {
        "x": 183.97373962402344,
        "y": 190.1514129638672
      },
      "direction": 0.8686946630477905,
      "dropPoint": {
        "x": 212.85513305664063,
        "y": 224.29470825195313
      },
      "position": {
        "x": 162.27659606933594,
        "y": 164.50125122070313
      },
      "predictedTarget": {
        "x": 235.19810485839844,
        "y": 250.70835876464844
      },
      "state": "Moving",
      "targetIndex": 2
    },
    {
      "aimPoint": {
        "x": 184.61956787109375,
        "y": 190.91490173339844
      },
      "direction": 0.8686946630477905,
      "dropPoint": {
        "x": 212.85513305664063,
        "y": 224.29470825195313
      },
      "position": {
        "x": 162.92242431640625,
        "y": 165.26473999023438
      },
      "predictedTarget": {
        "x": 235.19810485839844,
        "y": 250.70835876464844
      },
      "state": "Moving",
      "targetIndex": 2
    },
    {
      "aimPoint": {
        "x": 185.26539611816406,
        "y": 191.6783905029297
      },
      "direction": 0.8686946630477905,
      "dropPoint": {
        "x": 212.85513305664063,
        "y": 224.29470825195313
      },
      "position": {
        "x": 163.56825256347656,
        "y": 166.02822875976563
      },
      "predictedTarget": {
        "x": 235.19810485839844,
        "y": 250.70835876464844
      },
      "state": "Moving",
      "targetIndex": 2
    },
    {
      "aimPoint": {
        "x": 185.91122436523438,
        "y": 192.44187927246094
      },
      "direction": 0.8686947226524353,
      "dropPoint": {
        "x": 212.85513305664063,
        "y": 224.29470825195313
      },
      "position": {
        "x": 164.21408081054688,
        "y": 166.79171752929688
      },
      "predictedTarget": {
        "x": 235.19810485839844,
        "y": 250.70835876464844
      },
      "state": "Moving",
      "targetIndex": 2
    },
    {
      "aimPoint": {
        "x": 186.5570526123047,
        "y": 193.2053680419922
      },
      "direction": 0.8686947226524353,
      "dropPoint": {
        "x": 212.85513305664063,
        "y": 224.29470825195313
      },
      "position": {
        "x": 164.8599090576172,
        "y": 167.55520629882813
      },
      "predictedTarget": {
        "x": 235.19810485839844,
        "y": 250.70835876464844
      },
      "state": "Moving",
      "targetIndex": 2
    },
    {
      "aimPoint": {
        "x": 187.202880859375,
        "y": 193.96885681152344
      },
      "direction": 0.8686947226524353,
      "dropPoint": {
        "x": 212.85513305664063,
        "y": 224.29470825195313
      },
      "position": {
        "x": 165.5057373046875,
        "y": 168.31869506835938
      },
      "predictedTarget": {
        "x": 235.19810485839844,
        "y": 250.70835876464844
      },
      "state": "Moving",
      "targetIndex": 2
    },
    {
      "aimPoint": {
        "x": 187.8487091064453,
        "y": 194.7323455810547
      },
      "direction": 0.8686947822570801,
      "dropPoint": {
        "x": 212.85513305664063,
        "y": 224.29470825195313
      },
      "position": {
        "x": 166.1515655517578,
        "y": 169.08218383789063
      },
      "predictedTarget": {
        "x": 235.19810485839844,
        "y": 250.70835876464844
      },
      "state": "Moving",
      "targetIndex": 2
    },
    {
      "aimPoint": {
        "x": 188.49453735351563,
        "y": 195.49583435058594
      },
      "direction": 0.8686947822570801,
      "dropPoint": {
        "x": 212.85513305664063,
        "y": 224.29470825195313
      },
      "position": {
        "x": 166.79739379882813,
        "y": 169.84567260742188
      },
      "predictedTarget": {
        "x": 235.19810485839844,
        "y": 250.70835876464844
      },
      "state": "Moving",
      "targetIndex": 2
    },
    {
      "aimPoint": {
        "x": 189.14036560058594,
        "y": 196.2593231201172
      },
      "direction": 0.8686947822570801,
      "dropPoint": {
        "x": 212.85513305664063,
        "y": 224.29470825195313
      },
      "position": {
        "x": 167.44322204589844,
        "y": 170.60916137695313
      },
      "predictedTarget": {
        "x": 235.19810485839844,
        "y": 250.70835876464844
      },
      "state": "Moving",
      "targetIndex": 2
    },
    {
      "aimPoint": {
        "x": 189.78619384765625,
        "y": 197.02281188964844
      },
      "direction": 0.8686948418617249,
      "dropPoint": {
        "x": 212.85513305664063,
        "y": 224.29470825195313
      },
      "position": {
        "x": 168.08905029296875,
        "y": 171.37265014648438
      },
      "predictedTarget": {
        "x": 235.19810485839844,
        "y": 250.70835876464844
      },
      "state": "Moving",
      "targetIndex": 2
    },
    {
      "aimPoint": {
        "x": 190.43202209472656,
        "y": 197.7863006591797
      },
      "direction": 0.8686948418617249,
      "dropPoint": {
        "x": 212.85513305664063,
        "y": 224.29470825195313
      },
      "position": {
        "x": 168.73487854003906,
        "y": 172.13613891601563
      },
      "predictedTarget": {
        "x": 235.19810485839844,
        "y": 250.70835876464844
      },
      "state": "Moving",
      "targetIndex": 2
    },
    {
      "aimPoint": {
        "x": 191.07785034179688,
        "y": 198.54978942871094
      },
      "direction": 0.8686948418617249,
      "dropPoint": {
        "x": 212.85513305664063,
        "y": 224.29470825195313
      },
      "position": {
        "x": 169.38070678710938,
        "y": 172.89962768554688
      },
      "predictedTarget": {
        "x": 235.19810485839844,
        "y": 250.70835876464844
      },
      "state": "Moving",
      "targetIndex": 2
    },
    {
      "aimPoint": {
        "x": 191.7236785888672,
        "y": 199.3132781982422
      },
      "direction": 0.8686949014663696,
      "dropPoint": {
        "x": 212.85513305664063,
        "y": 224.29470825195313
      },
      "position": {
        "x": 170.0265350341797,
        "y": 173.66311645507813
      },
      "predictedTarget": {
        "x": 235.19810485839844,
        "y": 250.70835876464844
      },
      "state": "Moving",
      "targetIndex": 2
    },
    {
      "aimPoint": {
        "x": 192.3695068359375,
        "y": 200.0767822265625
      },
      "direction": 0.8686949014663696,
      "dropPoint": {
        "x": 212.85513305664063,
        "y": 224.29470825195313
      },
      "position": {
        "x": 170.67236328125,
        "y": 174.42660522460938
      },
      "predictedTarget": {
        "x": 235.19810485839844,
        "y": 250.70835876464844
      },
      "state": "Moving",
      "targetIndex": 2
    },
    {
      "aimPoint": {
        "x": 193.0153350830078,
        "y": 200.84027099609375
      },
      "direction": 0.8686949610710144,
      "dropPoint": {
        "x": 212.85513305664063,
        "y": 224.29470825195313
      },
      "position": {
        "x": 171.3181915283203,
        "y": 175.19009399414063
      },
      "predictedTarget": {
        "x": 235.19810485839844,
        "y": 250.70835876464844
      },
      "state": "Moving",
      "targetIndex": 2
    },
    {
      "aimPoint": {
        "x": 193.66116333007813,
        "y": 201.603759765625
      },
      "direction": 0.8686949610710144,
      "dropPoint": {
        "x": 212.85513305664063,
        "y": 224.29470825195313
      },
      "position": {
        "x": 171.96401977539063,
        "y": 175.95358276367188
      },
      "predictedTarget": {
        "x": 235.19810485839844,
        "y": 250.70835876464844
      },
      "state": "Moving",
      "targetIndex": 2
    },
    {
      "aimPoint": {
        "x": 194.30699157714844,
        "y": 202.36724853515625
      },
      "direction": 0.8686949610710144,
      "dropPoint": {
        "x": 212.85513305664063,
        "y": 224.29470825195313
      },
      "position": {
        "x": 172.60984802246094,
        "y": 176.71707153320313
      },
      "predictedTarget": {
        "x": 235.19810485839844,
        "y": 250.70835876464844
      },
      "state": "Moving",
      "targetIndex": 2
    },
    {
      "aimPoint": {
        "x": 194.95281982421875,
        "y": 203.1307373046875
      },
      "direction": 0.8686950206756592,
      "dropPoint": {
        "x": 212.85513305664063,
        "y": 224.29470825195313
      },
      "position": {
        "x": 173.25567626953125,
        "y": 177.48056030273438
      },
      "predictedTarget": {
        "x": 235.19810485839844,
        "y": 250.70835876464844
      },
      "state": "Moving",
      "targetIndex": 2
    },
    {
      "aimPoint": {
        "x": 195.59864807128906,
        "y": 203.89422607421875
      },
      "direction": 0.8686950206756592,
      "dropPoint": {
        "x": 212.85513305664063,
        "y": 224.29469299316406
      },
      "position": {
        "x": 173.90150451660156,
        "y": 178.24404907226563
      },
      "predictedTarget": {
        "x": 235.19810485839844,
        "y": 250.70835876464844
      },
      "state": "Moving",
      "targetIndex": 2
    },
    {
      "aimPoint": {
        "x": 196.24447631835938,
        "y": 204.65771484375
      },
      "direction": 0.868695080280304,
      "dropPoint": {
        "x": 212.85513305664063,
        "y": 224.29469299316406
      },
      "position": {
        "x": 174.54733276367188,
        "y": 179.00753784179688
      },
      "predictedTarget": {
        "x": 235.19810485839844,
        "y": 250.70835876464844
      },
      "state": "Moving",
      "targetIndex": 2
    },
    {
      "aimPoint": {
        "x": 196.89028930664063,
        "y": 205.42120361328125
      },
      "direction": 0.868695080280304,
      "dropPoint": {
        "x": 212.85513305664063,
        "y": 224.29469299316406
      },
      "position": {
        "x": 175.1931610107422,
        "y": 179.77102661132813
      },
      "predictedTarget": {
        "x": 235.19810485839844,
        "y": 250.70835876464844
      },
      "state": "Moving",
      "targetIndex": 2
    },
    {
      "aimPoint": {
        "x": 197.5361328125,
        "y": 206.1846923828125
      },
      "direction": 0.8686951398849487,
      "dropPoint": {
        "x": 212.85513305664063,
        "y": 224.29469299316406
      },
      "position": {
        "x": 175.8389892578125,
        "y": 180.53451538085938
      },
      "predictedTarget": {
        "x": 235.19810485839844,
        "y": 250.70835876464844
      },
      "state": "Moving",
      "targetIndex": 2
    },
    {
      "aimPoint": {
        "x": 198.18194580078125,
        "y": 206.94818115234375
      },
      "direction": 0.8686951398849487,
      "dropPoint": {
        "x": 212.8551483154297,
        "y": 224.29469299316406
      },
      "position": {
        "x": 176.4848175048828,
        "y": 181.29800415039063
      },
      "predictedTarget": {
        "x": 235.19810485839844,
        "y": 250.70835876464844
      },
      "state": "Moving",
      "targetIndex": 2
    },
    {
      "aimPoint": {
        "x": 198.82778930664063,
        "y": 207.711669921875
      },
      "direction": 0.8686951398849487,
      "dropPoint": {
        "x": 212.85513305664063,
        "y": 224.29469299316406
      },
      "position": {
        "x": 177.13064575195313,
        "y": 182.06149291992188
      },
      "predictedTarget": {
        "x": 235.19810485839844,
        "y": 250.70835876464844
      },
      "state": "Moving",
      "targetIndex": 2
    },
    {
      "aimPoint": {
        "x": 199.47360229492188,
        "y": 208.47515869140625
      },
      "direction": 0.8686951994895935,
      "dropPoint": {
        "x": 212.85513305664063,
        "y": 224.29469299316406
      },
      "position": {
        "x": 177.77647399902344,
        "y": 182.82498168945313
      },
      "predictedTarget": {
        "x": 235.19810485839844,
        "y": 250.70835876464844
      },
      "state": "Moving",
      "targetIndex": 2
    },
    {
      "aimPoint": {
        "x": 200.1194305419922,
        "y": 209.2386474609375
      },
      "direction": 0.8686951994895935,
      "dropPoint": {
        "x": 212.8551483154297,
        "y": 224.29469299316406
      },
      "position": {
        "x": 178.42230224609375,
        "y": 183.58847045898438
      },
      "predictedTarget": {
        "x": 235.19810485839844,
        "y": 250.70835876464844
      },
      "state": "Moving",
      "targetIndex": 2
    },
    {
      "aimPoint": {
        "x": 200.7652587890625,
        "y": 210.00213623046875
      },
      "direction": 0.8686952590942383,
      "dropPoint": {
        "x": 212.8551483154297,
        "y": 224.29469299316406
      },
      "position": {
        "x": 179.06813049316406,
        "y": 184.35195922851563
      },
      "predictedTarget": {
        "x": 235.19810485839844,
        "y": 250.70835876464844
      },
      "state": "Moving",
      "targetIndex": 2
    },
    {
      "aimPoint": {
        "x": 201.4110870361328,
        "y": 210.765625
      },
      "direction": 0.8686952590942383,
      "dropPoint": {
        "x": 212.8551483154297,
        "y": 224.29469299316406
      },
      "position": {
        "x": 179.71395874023438,
        "y": 185.11544799804688
      },
      "predictedTarget": {
        "x": 235.19810485839844,
        "y": 250.70835876464844
      },
      "state": "Moving",
      "targetIndex": 2
    },
    {
      "aimPoint": {
        "x": 202.05691528320313,
        "y": 211.52911376953125
      },
      "direction": 0.8686953186988831,
      "dropPoint": {
        "x": 212.8551483154297,
        "y": 224.29469299316406
      },
      "position": {
        "x": 180.3597869873047,
        "y": 185.87893676757813
      },
      "predictedTarget": {
        "x": 235.19810485839844,
        "y": 250.70835876464844
      },
      "state": "Moving",
      "targetIndex": 2
    },
    {
      "aimPoint": {
        "x": 202.70274353027344,
        "y": 212.2926025390625
      },
      "direction": 0.8686953783035278,
      "dropPoint": {
        "x": 212.8551483154297,
        "y": 224.29469299316406
      },
      "position": {
        "x": 181.005615234375,
        "y": 186.64242553710938
      },
      "predictedTarget": {
        "x": 235.19810485839844,
        "y": 250.70835876464844
      },
      "state": "Moving",
      "targetIndex": 2
    },
    {
      "aimPoint": {
        "x": 203.34857177734375,
        "y": 213.05609130859375
      },
      "direction": 0.8686953783035278,
      "dropPoint": {
        "x": 212.8551483154297,
        "y": 224.29469299316406
      },
      "position": {
        "x": 181.6514434814453,
        "y": 187.40591430664063
      },
      "predictedTarget": {
        "x": 235.19810485839844,
        "y": 250.70835876464844
      },
      "state": "Moving",
      "targetIndex": 2
    },
    {
      "aimPoint": {
        "x": 203.99440002441406,
        "y": 213.819580078125
      },
      "direction": 0.8686954379081726,
      "dropPoint": {
        "x": 212.8551483154297,
        "y": 224.29469299316406
      },
      "position": {
        "x": 182.29727172851563,
        "y": 188.16940307617188
      },
      "predictedTarget": {
        "x": 235.19810485839844,
        "y": 250.70835876464844
      },
      "state": "Moving",
      "targetIndex": 2
    },
    {
      "aimPoint": {
        "x": 204.64022827148438,
        "y": 214.58306884765625
      },
      "direction": 0.8686954379081726,
      "dropPoint": {
        "x": 212.8551483154297,
        "y": 224.29469299316406
      },
      "position": {
        "x": 182.94309997558594,
        "y": 188.93289184570313
      },
      "predictedTarget": {
        "x": 235.19810485839844,
        "y": 250.70835876464844
      },
      "state": "Moving",
      "targetIndex": 2
    },
    {
      "aimPoint": {
        "x": 205.2860565185547,
        "y": 215.3465576171875
      },
      "direction": 0.8686954975128174,
      "dropPoint": {
        "x": 212.8551483154297,
        "y": 224.29469299316406
      },
      "position": {
        "x": 183.58892822265625,
        "y": 189.69638061523438
      },
      "predictedTarget": {
        "x": 235.19810485839844,
        "y": 250.70835876464844
      },
      "state": "Moving",
      "targetIndex": 2
    },
    {
      "aimPoint": {
        "x": 205.931884765625,
        "y": 216.11004638671875
      },
      "direction": 0.8686954975128174,
      "dropPoint": {
        "x": 212.8551483154297,
        "y": 224.294677734375
      },
      "position": {
        "x": 184.23475646972656,
        "y": 190.45986938476563
      },
      "predictedTarget": {
        "x": 235.19810485839844,
        "y": 250.70835876464844
      },
      "state": "Moving",
      "targetIndex": 2
    },
    {
      "aimPoint": {
        "x": 206.5777130126953,
        "y": 216.87353515625
      },
      "direction": 0.8686956763267517,
      "dropPoint": {
        "x": 212.8551483154297,
        "y": 224.294677734375
      },
      "position": {
        "x": 184.88058471679688,
        "y": 191.22335815429688
      },
      "predictedTarget": {
        "x": 235.19810485839844,
        "y": 250.7083740234375
      },
      "state": "Moving",
      "targetIndex": 2
    },
    {
      "aimPoint": {
        "x": 207.22354125976563,
        "y": 217.63702392578125
      },
      "direction": 0.8686957359313965,
      "dropPoint": {
        "x": 212.8551483154297,
        "y": 224.294677734375
      },
      "position": {
        "x": 185.5264129638672,
        "y": 191.98684692382813
      },
      "predictedTarget": {
        "x": 235.19810485839844,
        "y": 250.7083740234375
      },
      "state": "Moving",
      "targetIndex": 2
    },
    {
      "aimPoint": {
        "x": 207.86935424804688,
        "y": 218.40052795410156
      },
      "direction": 0.8686957359313965,
      "dropPoint": {
        "x": 212.85516357421875,
        "y": 224.294677734375
      },
      "position": {
        "x": 186.1722412109375,
        "y": 192.75033569335938
      },
      "predictedTarget": {
        "x": 235.19810485839844,
        "y": 250.7083740234375
      },
      "state": "Moving",
      "targetIndex": 2
    },
    {
      "aimPoint": {
        "x": 208.51519775390625,
        "y": 219.1640167236328
      },
      "direction": 0.8686957955360413,
      "dropPoint": {
        "x": 212.85516357421875,
        "y": 224.294677734375
      },
      "position": {
        "x": 186.8180694580078,
        "y": 193.51382446289063
      },
      "predictedTarget": {
        "x": 235.19810485839844,
        "y": 250.7083740234375
      },
      "state": "Moving",
      "targetIndex": 2
    },
    {
      "aimPoint": {
        "x": 209.1610107421875,
        "y": 219.92750549316406
      },
      "direction": 0.868695855140686,
      "dropPoint": {
        "x": 212.85516357421875,
        "y": 224.29469299316406
      },
      "position": {
        "x": 187.46389770507813,
        "y": 194.27731323242188
      },
      "predictedTarget": {
        "x": 235.19810485839844,
        "y": 250.7083740234375
      },
      "state": "Moving",
      "targetIndex": 2
    },
    {
      "aimPoint": {
        "x": 209.8068389892578,
        "y": 220.6909942626953
      },
      "direction": 0.8686959147453308,
      "dropPoint": {
        "x": 212.85516357421875,
        "y": 224.29469299316406
      },
      "position": {
        "x": 188.10972595214844,
        "y": 195.04080200195313
      },
      "predictedTarget": {
        "x": 235.19810485839844,
        "y": 250.7083740234375
      },
      "state": "Moving",
      "targetIndex": 2
    },
    {
      "aimPoint": {
        "x": 210.45266723632813,
        "y": 221.45448303222656
      },
      "direction": 0.8686959147453308,
      "dropPoint": {
        "x": 212.85516357421875,
        "y": 224.29469299316406
      },
      "position": {
        "x": 188.75555419921875,
        "y": 195.80429077148438
      },
      "predictedTarget": {
        "x": 235.19810485839844,
        "y": 250.7083740234375
      },
      "state": "Moving",
      "targetIndex": 2
    },
    {
      "aimPoint": {
        "x": 211.09849548339844,
        "y": 222.2179718017578
      },
      "direction": 0.8686959743499756,
      "dropPoint": {
        "x": 212.85516357421875,
        "y": 224.29469299316406
      },
      "position": {
        "x": 189.40138244628906,
        "y": 196.56777954101563
      },
      "predictedTarget": {
        "x": 235.19810485839844,
        "y": 250.7083740234375
      },
      "state": "Moving",
      "targetIndex": 2
    },
    {
      "aimPoint": {
        "x": 211.74432373046875,
        "y": 222.98146057128906
      },
      "direction": 0.8686960339546204,
      "dropPoint": {
        "x": 212.85516357421875,
        "y": 224.29469299316406
      },
      "position": {
        "x": 190.04721069335938,
        "y": 197.33126831054688
      },
      "predictedTarget": {
        "x": 235.19810485839844,
        "y": 250.7083740234375
      },
      "state": "Moving",
      "targetIndex": 2
    },
    {
      "aimPoint": {
        "x": 212.39015197753906,
        "y": 223.7449493408203
      },
      "direction": 0.8686960935592651,
      "dropPoint": {
        "x": 212.85516357421875,
        "y": 224.29469299316406
      },
      "position": {
        "x": 190.6930389404297,
        "y": 198.09475708007813
      },
      "predictedTarget": {
        "x": 235.19810485839844,
        "y": 250.7083740234375
      },
      "state": "Moving",
      "targetIndex": 2
    },
    {
      "aimPoint": {
        "x": 213.03598022460938,
        "y": 224.50843811035156
      },
      "direction": 0.8686961531639099,
      "dropPoint": {
        "x": 212.85516357421875,
        "y": 224.29469299316406
      },
      "position": {
        "x": 191.3388671875,
        "y": 198.85824584960938
      },
      "predictedTarget": {
        "x": 235.19810485839844,
        "y": 250.7083740234375
      },
      "state": "Moving",
      "targetIndex": 2
    },
    {
      "aimPoint": {
        "x": 213.6818084716797,
        "y": 225.2719268798828
      },
      "direction": 0.8686961531639099,
      "dropPoint": {
        "x": 212.85516357421875,
        "y": 224.29469299316406
      },
      "position": {
        "x": 191.9846954345703,
        "y": 199.62173461914063
      },
      "predictedTarget": {
        "x": 235.19810485839844,
        "y": 250.7083740234375
      },
      "state": "Moving",
      "targetIndex": 2
    },
    {
      "aimPoint": {
        "x": 214.32763671875,
        "y": 226.03541564941406
      },
      "direction": 0.8686962127685547,
      "dropPoint": {
        "x": 212.85516357421875,
        "y": 224.29469299316406
      },
      "position": {
        "x": 192.63052368164063,
        "y": 200.38522338867188
      },
      "predictedTarget": {
        "x": 235.19810485839844,
        "y": 250.7083740234375
      },
      "state": "Moving",
      "targetIndex": 2
    },
    {
      "aimPoint": {
        "x": 214.9734649658203,
        "y": 226.7989044189453
      },
      "direction": 0.8686962723731995,
      "dropPoint": {
        "x": 212.85516357421875,
        "y": 224.294677734375
      },
      "position": {
        "x": 193.27635192871094,
        "y": 201.14871215820313
      },
      "predictedTarget": {
        "x": 235.19810485839844,
        "y": 250.7083740234375
      },
      "state": "Moving",
      "targetIndex": 2
    },
    {
      "aimPoint": {
        "x": 215.61929321289063,
        "y": 227.56240844726563
      },
      "direction": 0.8686963319778442,
      "dropPoint": {
        "x": 212.8551788330078,
        "y": 224.294677734375
      },
      "position": {
        "x": 193.92218017578125,
        "y": 201.91220092773438
      },
      "predictedTarget": {
        "x": 235.19810485839844,
        "y": 250.7083740234375
      },
      "state": "Moving",
      "targetIndex": 2
    },
    {
      "aimPoint": {
        "x": 216.26510620117188,
        "y": 228.32589721679688
      },
      "direction": 0.868696391582489,
      "dropPoint": {
        "x": 212.8551788330078,
        "y": 224.294677734375
      },
      "position": {
        "x": 194.56800842285156,
        "y": 202.67568969726563
      },
      "predictedTarget": {
        "x": 235.19810485839844,
        "y": 250.7083740234375
      },
      "state": "Moving",
      "targetIndex": 2
    },
    {
      "aimPoint": {
        "x": 216.9109344482422,
        "y": 229.08938598632813
      },
      "direction": 0.8686964511871338,
      "dropPoint": {
        "x": 212.8551788330078,
        "y": 224.294677734375
      },
      "position": {
        "x": 195.21383666992188,
        "y": 203.43917846679688
      },
      "predictedTarget": {
        "x": 235.19810485839844,
        "y": 250.7083740234375
      },
      "state": "Moving",
      "targetIndex": 2
    },
    {
      "aimPoint": {
        "x": 217.5567626953125,
        "y": 229.85287475585938
      },
      "direction": 0.8686965107917786,
      "dropPoint": {
        "x": 212.8551788330078,
        "y": 224.294677734375
      },
      "position": {
        "x": 195.8596649169922,
        "y": 204.20266723632813
      },
      "predictedTarget": {
        "x": 235.19810485839844,
        "y": 250.7083740234375
      },
      "state": "Moving",
      "targetIndex": 2
    },
    {
      "aimPoint": {
        "x": 218.2025909423828,
        "y": 230.61636352539063
      },
      "direction": 0.8686965703964233,
      "dropPoint": {
        "x": 212.8551788330078,
        "y": 224.294677734375
      },
      "position": {
        "x": 196.5054931640625,
        "y": 204.96615600585938
      },
      "predictedTarget": {
        "x": 235.19810485839844,
        "y": 250.7083740234375
      },
      "state": "Moving",
      "targetIndex": 2
    },
    {
      "aimPoint": {
        "x": 218.84841918945313,
        "y": 231.37985229492188
      },
      "direction": 0.8686966300010681,
      "dropPoint": {
        "x": 212.8551788330078,
        "y": 224.294677734375
      },
      "position": {
        "x": 197.1513214111328,
        "y": 205.72964477539063
      },
      "predictedTarget": {
        "x": 235.19810485839844,
        "y": 250.7083740234375
      },
      "state": "Moving",
      "targetIndex": 2
    },
    {
      "aimPoint": {
        "x": 219.49424743652344,
        "y": 232.14334106445313
      },
      "direction": 0.8686967492103577,
      "dropPoint": {
        "x": 212.8551788330078,
        "y": 224.294677734375
      },
      "position": {
        "x": 197.79714965820313,
        "y": 206.49313354492188
      },
      "predictedTarget": {
        "x": 235.19810485839844,
        "y": 250.7083740234375
      },
      "state": "Moving",
      "targetIndex": 2
    },
    {
      "aimPoint": {
        "x": 220.14007568359375,
        "y": 232.90682983398438
      },
      "direction": 0.8686968088150024,
      "dropPoint": {
        "x": 212.8551788330078,
        "y": 224.294677734375
      },
      "position": {
        "x": 198.44297790527344,
        "y": 207.25662231445313
      },
      "predictedTarget": {
        "x": 235.19810485839844,
        "y": 250.7083740234375
      },
      "state": "Moving",
      "targetIndex": 2
    },
    {
      "aimPoint": {
        "x": 220.785888671875,
        "y": 233.67031860351563
      },
      "direction": 0.8686968684196472,
      "dropPoint": {
        "x": 212.85519409179688,
        "y": 224.294677734375
      },
      "position": {
        "x": 199.08880615234375,
        "y": 208.02011108398438
      },
      "predictedTarget": {
        "x": 235.19810485839844,
        "y": 250.7083740234375
      },
      "state": "Moving",
      "targetIndex": 2
    },
    {
      "aimPoint": {
        "x": 221.43173217773438,
        "y": 234.43380737304688
      },
      "direction": 0.868696928024292,
      "dropPoint": {
        "x": 212.85519409179688,
        "y": 224.294677734375
      },
      "position": {
        "x": 199.73463439941406,
        "y": 208.78359985351563
      },
      "predictedTarget": {
        "x": 235.19810485839844,
        "y": 250.7083740234375
      },
      "state": "Moving",
      "targetIndex": 2
    },
    {
      "aimPoint": {
        "x": 222.07754516601563,
        "y": 235.19729614257813
      },
      "direction": 0.8686970472335815,
      "dropPoint": {
        "x": 212.85519409179688,
        "y": 224.29466247558594
      },
      "position": {
        "x": 200.38046264648438,
        "y": 209.54708862304688
      },
      "predictedTarget": {
        "x": 235.19810485839844,
        "y": 250.7083740234375
      },
      "state": "Moving",
      "targetIndex": 2
    },
    {
      "aimPoint": {
        "x": 222.72337341308594,
        "y": 235.96080017089844
      },
      "direction": 0.8686971068382263,
      "dropPoint": {
        "x": 212.85519409179688,
        "y": 224.29466247558594
      },
      "position": {
        "x": 201.0262908935547,
        "y": 210.31057739257813
      },
      "predictedTarget": {
        "x": 235.19810485839844,
        "y": 250.7083740234375
      },
      "state": "Moving",
      "targetIndex": 2
    },
    {
      "aimPoint": {
        "x": 223.36920166015625,
        "y": 236.7242889404297
      },
      "direction": 0.8686971664428711,
      "dropPoint": {
        "x": 212.85519409179688,
        "y": 224.29466247558594
      },
      "position": {
        "x": 201.672119140625,
        "y": 211.07406616210938
      },
      "predictedTarget": {
        "x": 235.19810485839844,
        "y": 250.7083740234375
      },
      "state": "Moving",
      "targetIndex": 2
    },
    {
      "aimPoint": {
        "x": 224.01502990722656,
        "y": 237.48777770996094
      },
      "direction": 0.8686972856521606,
      "dropPoint": {
        "x": 212.85519409179688,
        "y": 224.29466247558594
      },
      "position": {
        "x": 202.3179473876953,
        "y": 211.83755493164063
      },
      "predictedTarget": {
        "x": 235.19810485839844,
        "y": 250.7083740234375
      },
      "state": "Moving",
      "targetIndex": 2
    },
    {
      "aimPoint": {
        "x": 224.66085815429688,
        "y": 238.2512664794922
      },
      "direction": 0.8686973452568054,
      "dropPoint": {
        "x": 212.85519409179688,
        "y": 224.29466247558594
      },
      "position": {
        "x": 202.96377563476563,
        "y": 212.60104370117188
      },
      "predictedTarget": {
        "x": 235.19810485839844,
        "y": 250.7083740234375
      },
      "state": "Moving",
      "targetIndex": 2
    },
    {
      "aimPoint": {
        "x": 225.3066864013672,
        "y": 239.01475524902344
      },
      "direction": 0.868697464466095,
      "dropPoint": {
        "x": 212.85519409179688,
        "y": 224.29466247558594
      },
      "position": {
        "x": 203.60960388183594,
        "y": 213.36453247070313
      },
      "predictedTarget": {
        "x": 235.19810485839844,
        "y": 250.7083740234375
      },
      "state": "Moving",
      "targetIndex": 2
    },
    {
      "aimPoint": {
        "x": 225.9525146484375,
        "y": 239.7782440185547
      },
      "direction": 0.8686975836753845,
      "dropPoint": {
        "x": 212.85520935058594,
        "y": 224.29466247558594
      },
      "position": {
        "x": 204.25543212890625,
        "y": 214.12802124023438
      },
      "predictedTarget": {
        "x": 235.19810485839844,
        "y": 250.7083740234375
      },
      "state": "Moving",
      "targetIndex": 2
    },
    {
      "aimPoint": {
        "x": 226.59832763671875,
        "y": 240.54173278808594
      },
      "direction": 0.8686976432800293,
      "dropPoint": {
        "x": 212.85520935058594,
        "y": 224.29466247558594
      },
      "position": {
        "x": 204.90126037597656,
        "y": 214.89151000976563
      },
      "predictedTarget": {
        "x": 235.19810485839844,
        "y": 250.7083740234375
      },
      "state": "Moving",
      "targetIndex": 2
    },
    {
      "aimPoint": {
        "x": 227.24415588378906,
        "y": 241.3052215576172
      },
      "direction": 0.8686977624893188,
      "dropPoint": {
        "x": 212.85520935058594,
        "y": 224.29464721679688
      },
      "position": {
        "x": 205.54708862304688,
        "y": 215.65499877929688
      },
      "predictedTarget": {
        "x": 235.19810485839844,
        "y": 250.7083740234375
      },
      "state": "Moving",
      "targetIndex": 2
    },
    {
      "aimPoint": {
        "x": 227.88998413085938,
        "y": 242.0687255859375
      },
      "direction": 0.8686978816986084,
      "dropPoint": {
        "x": 212.85520935058594,
        "y": 224.29464721679688
      },
      "position": {
        "x": 206.1929168701172,
        "y": 216.41848754882813
      },
      "predictedTarget": {
        "x": 235.19810485839844,
        "y": 250.7083740234375
      },
      "state": "Moving",
      "targetIndex": 2
    },
    {
      "aimPoint": {
        "x": 228.5358123779297,
        "y": 242.83221435546875
      },
      "direction": 0.868698000907898,
      "dropPoint": {
        "x": 212.85520935058594,
        "y": 224.29464721679688
      },
      "position": {
        "x": 206.8387451171875,
        "y": 217.18197631835938
      },
      "predictedTarget": {
        "x": 235.19810485839844,
        "y": 250.7083740234375
      },
      "state": "Moving",
      "targetIndex": 2
    },
    {
      "aimPoint": {
        "x": 228.73150634765625,
        "y": 243.06387329101563
      },
      "direction": 0.8684118390083313,
      "dropPoint": {
        "x": 212.84901428222656,
        "y": 224.28318786621094
      },
      "position": {
        "x": 207.4847869873047,
        "y": 217.94528198242188
      },
      "predictedTarget": {
        "x": 235.199462890625,
        "y": 250.69052124023438
      },
      "state": "Moving",
      "targetIndex": 2
    },
    {
      "aimPoint": {
        "x": 228.72647094726563,
        "y": 243.04373168945313
      },
      "direction": 0.8679829835891724,
      "dropPoint": {
        "x": 212.83969116210938,
        "y": 224.26666259765625
      },
      "position": {
        "x": 208.1311492919922,
        "y": 218.70831298828125
      },
      "predictedTarget": {
        "x": 235.2014617919922,
        "y": 250.66441345214844
      },
      "state": "Moving",
      "targetIndex": 2
    },
    {
      "aimPoint": {
        "x": 228.72483825683594,
        "y": 243.02073669433594
      },
      "direction": 0.8675435185432434,
      "dropPoint": {
        "x": 212.83009338378906,
        "y": 224.2504119873047
      },
      "position": {
        "x": 208.77784729003906,
        "y": 219.47105407714844
      },
      "predictedTarget": {
        "x": 235.20346069335938,
        "y": 250.63832092285156
      },
      "state": "Moving",
      "targetIndex": 2
    },
    {
      "aimPoint": {
        "x": 228.72311401367188,
        "y": 242.997802734375
      },
      "direction": 0.8670924305915833,
      "dropPoint": {
        "x": 212.82020568847656,
        "y": 224.23439025878906
      },
      "position": {
        "x": 209.42489624023438,
        "y": 220.23350524902344
      },
      "predictedTarget": {
        "x": 235.20547485351563,
        "y": 250.61221313476563
      },
      "state": "Moving",
      "targetIndex": 2
    },
    {
      "aimPoint": {
        "x": 228.72129821777344,
        "y": 242.97496032714844
      },
      "direction": 0.8666303157806396,
      "dropPoint": {
        "x": 212.8100128173828,
        "y": 224.21865844726563
      },
      "position": {
        "x": 210.07229614257813,
        "y": 220.9956512451172
      },
      "predictedTarget": {
        "x": 235.2074737548828,
        "y": 250.58612060546875
      },
      "state": "Moving",
      "targetIndex": 2
    },
    {
      "aimPoint": {
        "x": 228.7193603515625,
        "y": 242.95220947265625
      },
      "direction": 0.8661556243896484,
      "dropPoint": {
        "x": 212.79949951171875,
        "y": 224.2031707763672
      },
      "position": {
        "x": 210.72006225585938,
        "y": 221.7574920654297
      },
      "predictedTarget": {
        "x": 235.20947265625,
        "y": 250.5600128173828
      },
      "state": "Moving",
      "targetIndex": 2
    },
    {
      "aimPoint": {
        "x": 228.71731567382813,
        "y": 242.9295654296875
      },
      "direction": 0.8656682372093201,
      "dropPoint": {
        "x": 212.7886505126953,
        "y": 224.18800354003906
      },
      "position": {
        "x": 211.36819458007813,
        "y": 222.51902770996094
      },
      "predictedTarget": {
        "x": 235.2114715576172,
        "y": 250.53392028808594
      },
      "state": "Moving",
      "targetIndex": 2
    },
    {
      "aimPoint": {
        "x": 228.71511840820313,
        "y": 242.90704345703125
      },
      "direction": 0.8651664853096008,
      "dropPoint": {
        "x": 212.77743530273438,
        "y": 224.17315673828125
      },
      "position": {
        "x": 212.01670837402344,
        "y": 223.2802276611328
      },
      "predictedTarget": {
        "x": 235.21347045898438,
        "y": 250.5078125
      },
      "state": "Moving",
      "targetIndex": 2
    },
    {
      "aimPoint": {
        "x": 228.71282958984375,
        "y": 242.88461303710938
      },
      "direction": 0.8646506667137146,
      "dropPoint": {
        "x": 212.76585388183594,
        "y": 224.1586456298828
      },
      "position": {
        "x": 212.66561889648438,
        "y": 224.0410919189453
      },
      "predictedTarget": {
        "x": 235.21546936035156,
        "y": 250.48171997070313
      },
      "state": "Moving",
      "targetIndex": 2
    },
    {
      "aimPoint": {
        "x": 228.71038818359375,
        "y": 242.8623046875
      },
      "direction": 0.864119291305542,
      "dropPoint": {
        "x": 212.75387573242188,
        "y": 224.14447021484375
      },
      "position": {
        "x": 213.31492614746094,
        "y": 224.80162048339844
      },
      "predictedTarget": {
        "x": 235.21746826171875,
        "y": 250.4556121826172
      },
      "state": "Moving",
      "targetIndex": 2
    }
  ],
  "totalSteps": 120
}