{
  "steps": [
    {
      "aimPoint": {
        "x": 269.669677734375,
        "y": 280.6336975097656
      },
      "direction": 1.0,
      "dropPoint": {
        "x": 315.7236022949219,
        "y": 316.65533447265625
      },
      "position": {
        "x": 250.0,
        "y": 250.0
      },
      "predictedTarget": {
        "x": 341.2839660644531,
        "y": 342.57806396484375
      },
      "state": 0,
      "targetIndex": 4,
      "timeSecSinceStart": 0.009999999776482582
    },
    {
      "aimPoint": {
        "x": 269.669677734375,
        "y": 280.6336975097656
      },
      "direction": 1.0,
      "dropPoint": {
        "x": 315.7236022949219,
        "y": 316.65533447265625
      },
      "position": {
        "x": 250.0,
        "y": 250.0
      },
      "predictedTarget": {
        "x": 341.2839660644531,
        "y": 342.57806396484375
      },
      "state": 0,
      "targetIndex": 4,
      "timeSecSinceStart": 0.08999998867511749
    },
    {
      "aimPoint": {
        "x": 271.588623046875,
        "y": 279.31298828125
      },
      "direction": 0.9279998540878296,
      "dropPoint": {
        "x": 315.7236022949219,
        "y": 316.65533447265625
      },
      "position": {
        "x": 250.0,
        "y": 250.0
      },
      "predictedTarget": {
        "x": 341.2839660644531,
        "y": 342.57806396484375
      },
      "state": 3,
      "targetIndex": 4,
      "timeSecSinceStart": 0.18000000715255737
    },
    {
      "aimPoint": {
        "x": 273.419189453125,
        "y": 277.87225341796875
      },
      "direction": 0.8719997406005859,
      "dropPoint": {
        "x": 315.7236022949219,
        "y": 316.65533447265625
      },
      "position": {
        "x": 250.0,
        "y": 250.0
      },
      "predictedTarget": {
        "x": 341.2839660644531,
        "y": 342.57806396484375
      },
      "state": 3,
      "targetIndex": 4,
      "timeSecSinceStart": 0.2500000298023224
    },
    {
      "aimPoint": {
        "x": 275.15386962890625,
        "y": 276.3173828125
      },
      "direction": 0.8079996109008789,
      "dropPoint": {
        "x": 315.7236022949219,
        "y": 316.65533447265625
      },
      "position": {
        "x": 250.0,
        "y": 250.0
      },
      "predictedTarget": {
        "x": 341.2839660644531,
        "y": 342.57806396484375
      },
      "state": 3,
      "targetIndex": 4,
      "timeSecSinceStart": 0.3299999535083771
    },
    {
      "aimPoint": {
        "x": 275.56036376953125,
        "y": 275.9227294921875
      },
      "direction": 0.7924364805221558,
      "dropPoint": {
        "x": 315.7236022949219,
        "y": 316.65533447265625
      },
      "position": {
        "x": 250.0,
        "y": 250.0
      },
      "predictedTarget": {
        "x": 341.2839660644531,
        "y": 342.57806396484375
      },
      "state": 3,
      "targetIndex": 4,
      "timeSecSinceStart": 0.40999987721443176
    },
    {
      "aimPoint": {
        "x": 275.56036376953125,
        "y": 275.9227294921875
      },
      "direction": 0.7924364805221558,
      "dropPoint": {
        "x": 315.7236022949219,
        "y": 316.65533447265625
      },
      "position": {
        "x": 250.0,
        "y": 250.0
      },
      "predictedTarget": {
        "x": 341.2839660644531,
        "y": 342.57806396484375
      },
      "state": 3,
      "targetIndex": 4,
      "timeSecSinceStart": 0.4799998104572296
    },
    {
      "aimPoint": {
        "x": 275.56036376953125,
        "y": 275.9227294921875
      },
      "direction": 0.7924364805221558,
      "dropPoint": {
        "x": 315.7236022949219,
        "y": 316.65533447265625
      },
      "position": {
        "x": 250.0,
        "y": 250.0
      },
      "predictedTarget": {
        "x": 341.2839660644531,
        "y": 342.57806396484375
      },
      "state": 0,
      "targetIndex": 4,
      "timeSecSinceStart": 0.5699997544288635
    },
    {
      "aimPoint": {
        "x": 275.57635498046875,
        "y": 275.93896484375
      },
      "direction": 0.7924364805221558,
      "dropPoint": {
        "x": 315.7440185546875,
        "y": 316.65545654296875
      },
      "position": {
        "x": 250.0159912109375,
        "y": 250.01622009277344
      },
      "predictedTarget": {
        "x": 341.30841064453125,
        "y": 342.5742492675781
      },
      "state": 1,
      "targetIndex": 4,
      "timeSecSinceStart": 0.659999668598175
    },
    {
      "aimPoint": {
        "x": 275.61492919921875,
        "y": 275.9700622558594
      },
      "direction": 0.792281985282898,
      "dropPoint": {
        "x": 315.7604064941406,
        "y": 316.6556091308594
      },
      "position": {
        "x": 250.05055236816406,
        "y": 250.05126953125
      },
      "predictedTarget": {
        "x": 341.3280029296875,
        "y": 342.57122802734375
      },
      "state": 1,
      "targetIndex": 4,
      "timeSecSinceStart": 0.7299996018409729
    },
    {
      "aimPoint": {
        "x": 275.6813659667969,
        "y": 276.03094482421875
      },
      "direction": 0.7921582460403442,
      "dropPoint": {
        "x": 315.7796325683594,
        "y": 316.6557312011719
      },
      "position": {
        "x": 250.11376953125,
        "y": 250.11532592773438
      },
      "predictedTarget": {
        "x": 341.3509826660156,
        "y": 342.567626953125
      },
      "state": 1,
      "targetIndex": 4,
      "timeSecSinceStart": 0.8099995255470276
    },
    {
      "aimPoint": {
        "x": 275.7864685058594,
        "y": 276.12994384765625
      },
      "direction": 0.7920129895210266,
      "dropPoint": {
        "x": 315.8018798828125,
        "y": 316.6559143066406
      },
      "position": {
        "x": 250.21511840820313,
        "y": 250.21803283691406
      },
      "predictedTarget": {
        "x": 341.3775939941406,
        "y": 342.5635070800781
      },
      "state": 1,
      "targetIndex": 4,
      "timeSecSinceStart": 0.8999994397163391
    },
    {
      "aimPoint": {
        "x": 275.9241943359375,
        "y": 276.2607421875
      },
      "direction": 0.7918446660041809,
      "dropPoint": {
        "x": 315.8248291015625,
        "y": 316.65606689453125
      },
      "position": {
        "x": 250.34848022460938,
        "y": 250.35313415527344
      },
      "predictedTarget": {
        "x": 341.405029296875,
        "y": 342.5592346191406
      },
      "state": 1,
      "targetIndex": 4,
      "timeSecSinceStart": 0.9899993538856506
    },
    {
      "aimPoint": {
        "x": 276.0940856933594,
        "y": 276.42376708984375
      },
      "direction": 0.7916707992553711,
      "dropPoint": {
        "x": 315.848388671875,
        "y": 316.65625
      },
      "position": {
        "x": 250.51388549804688,
        "y": 250.5206298828125
      },
      "predictedTarget": {
        "x": 341.4332580566406,
        "y": 342.5548400878906
      },
      "state": 1,
      "targetIndex": 4,
      "timeSecSinceStart": 1.079999327659607
    },
    {
      "aimPoint": {
        "x": 276.272705078125,
        "y": 276.59527587890625
      },
      "direction": 0.7914916276931763,
      "dropPoint": {
        "x": 315.86993408203125,
        "y": 316.6564636230469
      },
      "position": {
        "x": 250.68783569335938,
        "y": 250.6967010498047
      },
      "predictedTarget": {
        "x": 341.45904541015625,
        "y": 342.55084228515625
      },
      "state": 1,
      "targetIndex": 4,
      "timeSecSinceStart": 1.1599992513656616
    },
    {
      "aimPoint": {
        "x": 276.50286865234375,
        "y": 276.8197326660156
      },
      "direction": 0.7913278937339783,
      "dropPoint": {
        "x": 315.8948059082031,
        "y": 316.65667724609375
      },
      "position": {
        "x": 250.91378784179688,
        "y": 250.92535400390625
      },
      "predictedTarget": {
        "x": 341.4888000488281,
        "y": 342.54620361328125
      },
      "state": 1,
      "targetIndex": 4,
      "timeSecSinceStart": 1.2499991655349731
    },
    {
      "aimPoint": {
        "x": 276.7355651855469,
        "y": 277.0452880859375
      },
      "direction": 0.7911382913589478,
      "dropPoint": {
        "x": 315.9174499511719,
        "y": 316.6568908691406
      },
      "position": {
        "x": 251.14157104492188,
        "y": 251.15576171875
      },
      "predictedTarget": {
        "x": 341.51593017578125,
        "y": 342.5419921875
      },
      "state": 1,
      "targetIndex": 4,
      "timeSecSinceStart": 1.3299990892410278
    },
    {
      "aimPoint": {
        "x": 276.99322509765625,
        "y": 277.29681396484375
      },
      "direction": 0.7909651398658752,
      "dropPoint": {
        "x": 315.9406433105469,
        "y": 316.6571044921875
      },
      "position": {
        "x": 251.3947296142578,
        "y": 251.41172790527344
      },
      "predictedTarget": {
        "x": 341.5437316894531,
        "y": 342.53765869140625
      },
      "state": 1,
      "targetIndex": 4,
      "timeSecSinceStart": 1.4099990129470825
    },
    {
      "aimPoint": {
        "x": 277.27630615234375,
        "y": 277.57379150390625
      },
      "direction": 0.7907873392105103,
      "dropPoint": {
        "x": 315.96435546875,
        "y": 316.6573486328125
      },
      "position": {
        "x": 251.67323303222656,
        "y": 251.69325256347656
      },
      "predictedTarget": {
        "x": 341.5721435546875,
        "y": 342.5332336425781
      },
      "state": 1,
      "targetIndex": 4,
      "timeSecSinceStart": 1.4899989366531372
    },
    {
      "aimPoint": {
        "x": 277.58489990234375,
        "y": 277.8761901855469
      },
      "direction": 0.7906048893928528,
      "dropPoint": {
        "x": 315.98858642578125,
        "y": 316.65765380859375
      },
      "position": {
        "x": 251.9770965576172,
        "y": 252.0003204345703
      },
      "predictedTarget": {
        "x": 341.6012268066406,
        "y": 342.5287170410156
      },
      "state": 1,
      "targetIndex": 4,
      "timeSecSinceStart": 1.569998860359192
    },
    {
      "aimPoint": {
        "x": 277.87646484375,
        "y": 278.1610107421875
      },
      "direction": 0.7904175519943237,
      "dropPoint": {
        "x": 316.0101623535156,
        "y": 316.65789794921875
      },
      "position": {
        "x": 252.2637939453125,
        "y": 252.28993225097656
      },
      "predictedTarget": {
        "x": 341.6271667480469,
        "y": 342.5246887207031
      },
      "state": 1,
      "targetIndex": 4,
      "timeSecSinceStart": 1.6399987936019897
    },
    {
      "aimPoint": {
        "x": 278.2779541015625,
        "y": 278.55780029296875
      },
      "direction": 0.7902500033378601,
      "dropPoint": {
        "x": 316.03857421875,
        "y": 316.65826416015625
      },
      "position": {
        "x": 252.6609649658203,
        "y": 252.69100952148438
      },
      "predictedTarget": {
        "x": 341.6612854003906,
        "y": 342.5193786621094
      },
      "state": 1,
      "targetIndex": 4,
      "timeSecSinceStart": 1.7299987077713013
    },
    {
      "aimPoint": {
        "x": 278.7627258300781,
        "y": 279.0356140136719
      },
      "direction": 0.7900285124778748,
      "dropPoint": {
        "x": 316.0708312988281,
        "y": 316.6587219238281
      },
      "position": {
        "x": 253.13999938964844,
        "y": 253.17449951171875
      },
      "predictedTarget": {
        "x": 341.7001037597656,
        "y": 342.5133361816406
      },
      "state": 1,
      "targetIndex": 4,
      "timeSecSinceStart": 1.8299986124038696
    },
    {
      "aimPoint": {
        "x": 279.1811218261719,
        "y": 279.444580078125
      },
      "direction": 0.789775550365448,
      "dropPoint": {
        "x": 316.0972595214844,
        "y": 316.6590881347656
      },
      "position": {
        "x": 253.55186462402344,
        "y": 253.5899658203125
      },
      "predictedTarget": {
        "x": 341.7319030761719,
        "y": 342.5083923339844
      },
      "state": 1,
      "targetIndex": 4,
      "timeSecSinceStart": 1.9099985361099243
    },
    {
      "aimPoint": {
        "x": 279.6802062988281,
        "y": 279.9371337890625
      },
      "direction": 0.7895675301551819,
      "dropPoint": {
        "x": 316.1275634765625,
        "y": 316.6595764160156
      },
      "position": {
        "x": 254.04556274414063,
        "y": 254.08782958984375
      },
      "predictedTarget": {
        "x": 341.7684326171875,
        "y": 342.5027160644531
      },
      "state": 1,
      "targetIndex": 4,
      "timeSecSinceStart": 1.9999984502792358
    },
    {
      "aimPoint": {
        "x": 280.15234375,
        "y": 280.4005432128906
      },
      "direction": 0.7893269658088684,
      "dropPoint": {
        "x": 316.1550598144531,
        "y": 316.6600341796875
      },
      "position": {
        "x": 254.51150512695313,
        "y": 254.55740356445313
      },
      "predictedTarget": {
        "x": 341.80157470703125,
        "y": 342.49755859375
      },
      "state": 1,
      "targetIndex": 4,
      "timeSecSinceStart": 2.07999849319458
    },
    {
      "aimPoint": {
        "x": 280.7125549316406,
        "y": 280.9536437988281
      },
      "direction": 0.7891080379486084,
      "dropPoint": {
        "x": 316.18658447265625,
        "y": 316.66064453125
      },
      "position": {
        "x": 255.0660400390625,
        "y": 255.11611938476563
      },
      "predictedTarget": {
        "x": 341.83966064453125,
        "y": 342.49163818359375
      },
      "state": 1,
      "targetIndex": 4,
      "timeSecSinceStart": 2.1699984073638916
    },
    {
      "aimPoint": {
        "x": 281.305908203125,
        "y": 281.5379943847656
      },
      "direction": 0.7888543605804443,
      "dropPoint": {
        "x": 316.2187194824219,
        "y": 316.6612548828125
      },
      "position": {
        "x": 255.65284729003906,
        "y": 255.70700073242188
      },
      "predictedTarget": {
        "x": 341.8785095214844,
        "y": 342.4855651855469
      },
      "state": 1,
      "targetIndex": 4,
      "timeSecSinceStart": 2.259998321533203
    },
    {
      "aimPoint": {
        "x": 281.8613586425781,
        "y": 282.0836181640625
      },
      "direction": 0.7885940670967102,
      "dropPoint": {
        "x": 316.2478332519531,
        "y": 316.661865234375
      },
      "position": {
        "x": 256.2015686035156,
        "y": 256.25927734375
      },
      "predictedTarget": {
        "x": 341.91375732421875,
        "y": 342.4801025390625
      },
      "state": 1,
      "targetIndex": 4,
      "timeSecSinceStart": 2.339998245239258
    },
    {
      "aimPoint": {
        "x": 282.5154113769531,
        "y": 282.7291564941406
      },
      "direction": 0.7883564829826355,
      "dropPoint": {
        "x": 316.28118896484375,
        "y": 316.66259765625
      },
      "position": {
        "x": 256.8494873046875,
        "y": 256.9109191894531
      },
      "predictedTarget": {
        "x": 341.95416259765625,
        "y": 342.47381591796875
      },
      "state": 1,
      "targetIndex": 4,
      "timeSecSinceStart": 2.4299981594085693
    },
    {
      "aimPoint": {
        "x": 283.0486145019531,
        "y": 283.25115966796875
      },
      "direction": 0.788083016872406,
      "dropPoint": {
        "x": 316.3075256347656,
        "y": 316.6632385253906
      },
      "position": {
        "x": 257.3756408691406,
        "y": 257.43994140625
      },
      "predictedTarget": {
        "x": 341.98614501953125,
        "y": 342.4688415527344
      },
      "state": 1,
      "targetIndex": 4,
      "timeSecSinceStart": 2.499998092651367
    },
    {
      "aimPoint": {
        "x": 283.75958251953125,
        "y": 283.9542541503906
      },
      "direction": 0.7878645658493042,
      "dropPoint": {
        "x": 316.34197998046875,
        "y": 316.6640930175781
      },
      "position": {
        "x": 258.0809631347656,
        "y": 258.1486511230469
      },
      "predictedTarget": {
        "x": 342.02801513671875,
        "y": 342.4623107910156
      },
      "state": 1,
      "targetIndex": 4,
      "timeSecSinceStart": 2.5899980068206787
    },
    {
      "aimPoint": {
        "x": 284.4211730957031,
        "y": 284.6037292480469
      },
      "direction": 0.7875769734382629,
      "dropPoint": {
        "x": 316.37310791015625,
        "y": 316.6649169921875
      },
      "position": {
        "x": 258.7351379394531,
        "y": 258.8055114746094
      },
      "predictedTarget": {
        "x": 342.0658874511719,
        "y": 342.4564208984375
      },
      "state": 1,
      "targetIndex": 4,
      "timeSecSinceStart": 2.6699979305267334
    },
    {
      "aimPoint": {
        "x": 285.1942138671875,
        "y": 285.3663330078125
      },
      "direction": 0.7873154878616333,
      "dropPoint": {
        "x": 316.40863037109375,
        "y": 316.6659851074219
      },
      "position": {
        "x": 259.5014343261719,
        "y": 259.5748291015625
      },
      "predictedTarget": {
        "x": 342.1092529296875,
        "y": 342.4496765136719
      },
      "state": 1,
      "targetIndex": 4,
      "timeSecSinceStart": 2.759997844696045
    },
    {
      "aimPoint": {
        "x": 286.09149169921875,
        "y": 286.2509460449219
      },
      "direction": 0.7870118021965027,
      "dropPoint": {
        "x": 316.4488220214844,
        "y": 316.66729736328125
      },
      "position": {
        "x": 260.390869140625,
        "y": 260.4672546386719
      },
      "predictedTarget": {
        "x": 342.1584167480469,
        "y": 342.4420471191406
      },
      "state": 1,
      "targetIndex": 4,
      "timeSecSinceStart": 2.8599977493286133
    },
    {
      "aimPoint": {
        "x": 286.9351806640625,
        "y": 287.0788879394531
      },
      "direction": 0.786663830280304,
      "dropPoint": {
        "x": 316.485595703125,
        "y": 316.6685485839844
      },
      "position": {
        "x": 261.2255859375,
        "y": 261.30413818359375
      },
      "predictedTarget": {
        "x": 342.2034912109375,
        "y": 342.4350280761719
      },
      "state": 1,
      "targetIndex": 4,
      "timeSecSinceStart": 2.949997663497925
    },
    {
      "aimPoint": {
        "x": 287.712890625,
        "y": 287.8414001464844
      },
      "direction": 0.7863419055938721,
      "dropPoint": {
        "x": 316.5188293457031,
        "y": 316.66973876953125
      },
      "position": {
        "x": 261.9949951171875,
        "y": 262.0749206542969
      },
      "predictedTarget": {
        "x": 342.2442626953125,
        "y": 342.4286804199219
      },
      "state": 1,
      "targetIndex": 4,
      "timeSecSinceStart": 3.0299975872039795
    },
    {
      "aimPoint": {
        "x": 288.5154724121094,
        "y": 288.6298828125
      },
      "direction": 0.7860487699508667,
      "dropPoint": {
        "x": 316.552490234375,
        "y": 316.6710510253906
      },
      "position": {
        "x": 262.7900390625,
        "y": 262.8709411621094
      },
      "predictedTarget": {
        "x": 342.2856750488281,
        "y": 342.4222412109375
      },
      "state": 1,
      "targetIndex": 4,
      "timeSecSinceStart": 3.109997510910034
    },
    {
      "aimPoint": {
        "x": 289.3439025878906,
        "y": 289.44329833984375
      },
      "direction": 0.7857481241226196,
      "dropPoint": {
        "x": 316.58660888671875,
        "y": 316.6724548339844
      },
      "position": {
        "x": 263.6107177734375,
        "y": 263.6921081542969
      },
      "predictedTarget": {
        "x": 342.3277282714844,
        "y": 342.41571044921875
      },
      "state": 1,
      "targetIndex": 4,
      "timeSecSinceStart": 3.189997434616089
    },
    {
      "aimPoint": {
        "x": 290.3028564453125,
        "y": 290.3864440917969
      },
      "direction": 0.7854400277137756,
      "dropPoint": {
        "x": 316.6160583496094,
        "y": 316.6737365722656
      },
      "position": {
        "x": 264.5617370605469,
        "y": 264.6431884765625
      },
      "predictedTarget": {
        "x": 342.3641357421875,
        "y": 342.4100341796875
      },
      "state": 1,
      "targetIndex": 4,
      "timeSecSinceStart": 3.2799973487854004
    },
    {
      "aimPoint": {
        "x": 291.0523681640625,
        "y": 291.121826171875
      },
      "direction": 0.7851696014404297,
      "dropPoint": {
        "x": 316.6311340332031,
        "y": 316.6744689941406
      },
      "position": {
        "x": 265.4103698730469,
        "y": 265.4915771484375
      },
      "predictedTarget": {
        "x": 342.3828430175781,
        "y": 342.4071350097656
      },
      "state": 4,
      "targetIndex": 4,
      "timeSecSinceStart": 3.359997272491455
    },
    {
      "aimPoint": {
        "x": 292.1170654296875,
        "y": 292.17840576171875
      },
      "direction": 0.7850286364555359,
      "dropPoint": {
        "x": 316.6526184082031,
        "y": 316.6755065917969
      },
      "position": {
        "x": 266.3653564453125,
        "y": 266.44573974609375
      },
      "predictedTarget": {
        "x": 342.4095458984375,
        "y": 342.4029541015625
      },
      "state": 4,
      "targetIndex": 4,
      "timeSecSinceStart": 3.4499971866607666
    },
    {
      "aimPoint": {
        "x": 292.9714050292969,
        "y": 293.0213317871094
      },
      "direction": 0.7848259806632996,
      "dropPoint": {
        "x": 316.6697998046875,
        "y": 316.6764221191406
      },
      "position": {
        "x": 267.2144775390625,
        "y": 267.29388427734375
      },
      "predictedTarget": {
        "x": 342.4309387207031,
        "y": 342.399658203125
      },
      "state": 4,
      "targetIndex": 4,
      "timeSecSinceStart": 3.5299971103668213
    },
    {
      "aimPoint": {
        "x": 293.7185974121094,
        "y": 293.759033203125
      },
      "direction": 0.7846618294715881,
      "dropPoint": {
        "x": 316.68475341796875,
        "y": 316.67724609375
      },
      "position": {
        "x": 268.0635986328125,
        "y": 268.14178466796875
      },
      "predictedTarget": {
        "x": 342.4496154785156,
        "y": 342.396728515625
      },
      "state": 4,
      "targetIndex": 4,
      "timeSecSinceStart": 3.609997034072876
    },
    {
      "aimPoint": {
        "x": 294.5716552734375,
        "y": 294.6031799316406
      },
      "direction": 0.7845165729522705,
      "dropPoint": {
        "x": 316.7018127441406,
        "y": 316.6782531738281
      },
      "position": {
        "x": 268.8067932128906,
        "y": 268.8836975097656
      },
      "predictedTarget": {
        "x": 342.47100830078125,
        "y": 342.3934020996094
      },
      "state": 4,
      "targetIndex": 4,
      "timeSecSinceStart": 3.679996967315674
    },
    {
      "aimPoint": {
        "x": 295.5315246582031,
        "y": 295.5524597167969
      },
      "direction": 0.7843483090400696,
      "dropPoint": {
        "x": 316.7209167480469,
        "y": 316.6794738769531
      },
      "position": {
        "x": 269.7623291015625,
        "y": 269.8373107910156
      },
      "predictedTarget": {
        "x": 342.4950256347656,
        "y": 342.3896789550781
      },
      "state": 4,
      "targetIndex": 4,
      "timeSecSinceStart": 3.7699968814849854
    },
    {
      "aimPoint": {
        "x": 296.38604736328125,
        "y": 296.39495849609375
      },
      "direction": 0.7841569781303406,
      "dropPoint": {
        "x": 316.7378845214844,
        "y": 316.6805419921875
      },
      "position": {
        "x": 270.6119384765625,
        "y": 270.6847229003906
      },
      "predictedTarget": {
        "x": 342.51641845703125,
        "y": 342.3863525390625
      },
      "state": 4,
      "targetIndex": 4,
      "timeSecSinceStart": 3.84999680519104
    },
    {
      "aimPoint": {
        "x": 297.3462829589844,
        "y": 297.3438720703125
      },
      "direction": 0.7839856147766113,
      "dropPoint": {
        "x": 316.7568359375,
        "y": 316.681884765625
      },
      "position": {
        "x": 271.5677490234375,
        "y": 271.6380615234375
      },
      "predictedTarget": {
        "x": 342.5404357910156,
        "y": 342.3825988769531
      },
      "state": 4,
      "targetIndex": 4,
      "timeSecSinceStart": 3.9399967193603516
    },
    {
      "aimPoint": {
        "x": 298.2012023925781,
        "y": 298.1859436035156
      },
      "direction": 0.7836116552352905,
      "dropPoint": {
        "x": 316.773681640625,
        "y": 316.68310546875
      },
      "position": {
        "x": 272.52386474609375,
        "y": 272.5910949707031
      },
      "predictedTarget": {
        "x": 342.56182861328125,
        "y": 342.3792724609375
      },
      "state": 4,
      "targetIndex": 4,
      "timeSecSinceStart": 4.0299973487854
    },
    {
      "aimPoint": {
        "x": 299.26837158203125,
        "y": 299.24005126953125
      },
      "direction": 0.7836116552352905,
      "dropPoint": {
        "x": 316.794677734375,
        "y": 316.6846923828125
      },
      "position": {
        "x": 273.480224609375,
        "y": 273.54388427734375
      },
      "predictedTarget": {
        "x": 342.5885314941406,
        "y": 342.3751220703125
      },
      "state": 4,
      "targetIndex": 4,
      "timeSecSinceStart": 4.119999408721924
    },
    {
      "aimPoint": {
        "x": 300.230712890625,
        "y": 300.1871032714844
      },
      "direction": 0.7833895683288574,
      "dropPoint": {
        "x": 316.8135070800781,
        "y": 316.68621826171875
      },
      "position": {
        "x": 274.4368591308594,
        "y": 274.4966735839844
      },
      "predictedTarget": {
        "x": 342.6125793457031,
        "y": 342.37139892578125
      },
      "state": 4,
      "targetIndex": 4,
      "timeSecSinceStart": 4.210001468658447
    },
    {
      "aimPoint": {
        "x": 301.0862731933594,
        "y": 301.0285339355469
      },
      "direction": 0.7831857800483704,
      "dropPoint": {
        "x": 316.83013916015625,
        "y": 316.6876525878906
      },
      "position": {
        "x": 275.2872009277344,
        "y": 275.3433532714844
      },
      "predictedTarget": {
        "x": 342.6339416503906,
        "y": 342.3680725097656
      },
      "state": 4,
      "targetIndex": 4,
      "timeSecSinceStart": 4.290003299713135
    },
    {
      "aimPoint": {
        "x": 301.83526611328125,
        "y": 301.764404296875
      },
      "direction": 0.7830016613006592,
      "dropPoint": {
        "x": 316.8446960449219,
        "y": 316.68890380859375
      },
      "position": {
        "x": 276.1377868652344,
        "y": 276.1897888183594
      },
      "predictedTarget": {
        "x": 342.65264892578125,
        "y": 342.3651428222656
      },
      "state": 4,
      "targetIndex": 4,
      "timeSecSinceStart": 4.370005130767822
    },
    {
      "aimPoint": {
        "x": 302.90264892578125,
        "y": 302.8182678222656
      },
      "direction": 0.7828397154808044,
      "dropPoint": {
        "x": 316.86529541015625,
        "y": 316.69085693359375
      },
      "position": {
        "x": 277.0946960449219,
        "y": 277.14202880859375
      },
      "predictedTarget": {
        "x": 342.6793518066406,
        "y": 342.3609924316406
      },
      "state": 4,
      "targetIndex": 4,
      "timeSecSinceStart": 4.460007190704346
    },
    {
      "aimPoint": {
        "x": 303.75958251953125,
        "y": 303.6583251953125
      },
      "direction": 0.7826024293899536,
      "dropPoint": {
        "x": 316.8817443847656,
        "y": 316.6925048828125
      },
      "position": {
        "x": 277.9455261230469,
        "y": 277.98822021484375
      },
      "predictedTarget": {
        "x": 342.7007141113281,
        "y": 342.357666015625
      },
      "state": 4,
      "targetIndex": 4,
      "timeSecSinceStart": 4.540009021759033
    },
    {
      "aimPoint": {
        "x": 304.5091857910156,
        "y": 304.3935852050781
      },
      "direction": 0.7824108004570007,
      "dropPoint": {
        "x": 316.8961181640625,
        "y": 316.6939392089844
      },
      "position": {
        "x": 278.6902160644531,
        "y": 278.7284240722656
      },
      "predictedTarget": {
        "x": 342.71942138671875,
        "y": 342.3547668457031
      },
      "state": 4,
      "targetIndex": 4,
      "timeSecSinceStart": 4.610010623931885
    },
    {
      "aimPoint": {
        "x": 305.47125244140625,
        "y": 305.3409423828125
      },
      "direction": 0.7822422981262207,
      "dropPoint": {
        "x": 316.9145202636719,
        "y": 316.6958923339844
      },
      "position": {
        "x": 279.64794921875,
        "y": 279.68011474609375
      },
      "predictedTarget": {
        "x": 342.74346923828125,
        "y": 342.35101318359375
      },
      "state": 4,
      "targetIndex": 4,
      "timeSecSinceStart": 4.700012683868408
    },
    {
      "aimPoint": {
        "x": 306.3282165527344,
        "y": 306.1809387207031
      },
      "direction": 0.7820218801498413,
      "dropPoint": {
        "x": 316.9307556152344,
        "y": 316.6977233886719
      },
      "position": {
        "x": 280.499267578125,
        "y": 280.52581787109375
      },
      "predictedTarget": {
        "x": 342.76483154296875,
        "y": 342.34771728515625
      },
      "state": 4,
      "targetIndex": 4,
      "timeSecSinceStart": 4.780014514923096
    },
    {
      "aimPoint": {
        "x": 307.1849060058594,
        "y": 307.0212707519531
      },
      "direction": 0.7818227410316467,
      "dropPoint": {
        "x": 316.9469909667969,
        "y": 316.6995849609375
      },
      "position": {
        "x": 281.457275390625,
        "y": 281.4769592285156
      },
      "predictedTarget": {
        "x": 342.78619384765625,
        "y": 342.3443908691406
      },
      "state": 4,
      "targetIndex": 4,
      "timeSecSinceStart": 4.870016574859619
    },
    {
      "aimPoint": {
        "x": 308.1482849121094,
        "y": 307.96697998046875
      },
      "direction": 0.7816218733787537,
      "dropPoint": {
        "x": 316.96514892578125,
        "y": 316.7017517089844
      },
      "position": {
        "x": 282.30908203125,
        "y": 282.3221740722656
      },
      "predictedTarget": {
        "x": 342.81024169921875,
        "y": 342.34063720703125
      },
      "state": 4,
      "targetIndex": 4,
      "timeSecSinceStart": 4.950018405914307
    },
    {
      "aimPoint": {
        "x": 309.0059814453125,
        "y": 308.8062744140625
      },
      "direction": 0.7813930511474609,
      "dropPoint": {
        "x": 316.9811706542969,
        "y": 316.7038269042969
      },
      "position": {
        "x": 283.160888671875,
        "y": 283.1673889160156
      },
      "predictedTarget": {
        "x": 342.83160400390625,
        "y": 342.3373107910156
      },
      "state": 4,
      "targetIndex": 4,
      "timeSecSinceStart": 5.030020236968994
    },
    {
      "aimPoint": {
        "x": 309.9698791503906,
        "y": 309.75146484375
      },
      "direction": 0.781184196472168,
      "dropPoint": {
        "x": 316.9991455078125,
        "y": 316.70623779296875
      },
      "position": {
        "x": 284.11944580078125,
        "y": 284.11798095703125
      },
      "predictedTarget": {
        "x": 342.85565185546875,
        "y": 342.3335876464844
      },
      "state": 4,
      "targetIndex": 4,
      "timeSecSinceStart": 5.120022296905518
    },
    {
      "aimPoint": {
        "x": 310.8282470703125,
        "y": 310.5900573730469
      },
      "direction": 0.7809467911720276,
      "dropPoint": {
        "x": 317.0150146484375,
        "y": 316.70843505859375
      },
      "position": {
        "x": 284.97174072265625,
        "y": 284.96270751953125
      },
      "predictedTarget": {
        "x": 342.87701416015625,
        "y": 342.33026123046875
      },
      "state": 4,
      "targetIndex": 4,
      "timeSecSinceStart": 5.200024127960205
    },
    {
      "aimPoint": {
        "x": 311.686279296875,
        "y": 311.42901611328125
      },
      "direction": 0.7807334661483765,
      "dropPoint": {
        "x": 317.0308837890625,
        "y": 316.7106628417969
      },
      "position": {
        "x": 285.82427978515625,
        "y": 285.80718994140625
      },
      "predictedTarget": {
        "x": 342.89837646484375,
        "y": 342.3269348144531
      },
      "state": 4,
      "targetIndex": 4,
      "timeSecSinceStart": 5.280025959014893
    },
    {
      "aimPoint": {
        "x": 312.65087890625,
        "y": 312.3735046386719
      },
      "direction": 0.7805180549621582,
      "dropPoint": {
        "x": 317.0484924316406,
        "y": 316.71337890625
      },
      "position": {
        "x": 286.78338623046875,
        "y": 286.7572326660156
      },
      "predictedTarget": {
        "x": 342.92242431640625,
        "y": 342.32318115234375
      },
      "state": 4,
      "targetIndex": 4,
      "timeSecSinceStart": 5.370028018951416
    },
    {
      "aimPoint": {
        "x": 313.6166687011719,
        "y": 313.3167724609375
      },
      "direction": 0.7802678346633911,
      "dropPoint": {
        "x": 317.0660705566406,
        "y": 316.71624755859375
      },
      "position": {
        "x": 287.7427673339844,
        "y": 287.7070007324219
      },
      "predictedTarget": {
        "x": 342.94647216796875,
        "y": 342.3194580078125
      },
      "state": 4,
      "targetIndex": 4,
      "timeSecSinceStart": 5.4600300788879395
    },
    {
      "aimPoint": {
        "x": 314.4761962890625,
        "y": 314.1542053222656
      },
      "direction": 0.7800142168998718,
      "dropPoint": {
        "x": 317.0815734863281,
        "y": 316.71881103515625
      },
      "position": {
        "x": 288.5957946777344,
        "y": 288.5509948730469
      },
      "predictedTarget": {
        "x": 342.96783447265625,
        "y": 342.3161315917969
      },
      "state": 4,
      "targetIndex": 4,
      "timeSecSinceStart": 5.540031909942627
    },
    {
      "aimPoint": {
        "x": 315.54864501953125,
        "y": 315.2030029296875
      },
      "direction": 0.7797858715057373,
      "dropPoint": {
        "x": 317.1008605957031,
        "y": 316.72216796875
      },
      "position": {
        "x": 289.6623840332031,
        "y": 289.6056823730469
      },
      "predictedTarget": {
        "x": 342.9945373535156,
        "y": 342.3119812011719
      },
      "state": 4,
      "targetIndex": 4,
      "timeSecSinceStart": 5.640034198760986
    },
    {
      "aimPoint": {
        "x": 316.5162658691406,
        "y": 316.1444396972656
      },
      "direction": 0.7794960737228394,
      "dropPoint": {
        "x": 317.11810302734375,
        "y": 316.7253112792969
      },
      "position": {
        "x": 290.6225891113281,
        "y": 290.55462646484375
      },
      "predictedTarget": {
        "x": 343.0185852050781,
        "y": 342.3082275390625
      },
      "state": 4,
      "targetIndex": 4,
      "timeSecSinceStart": 5.73003625869751
    },
    {
      "aimPoint": {
        "x": 317.4835510253906,
        "y": 317.0862121582031
      },
      "direction": 0.7792302370071411,
      "dropPoint": {
        "x": 317.13525390625,
        "y": 316.7285461425781
      },
      "position": {
        "x": 291.58306884765625,
        "y": 291.5032958984375
      },
      "predictedTarget": {
        "x": 343.0426330566406,
        "y": 342.3044738769531
      },
      "state": 4,
      "targetIndex": 4,
      "timeSecSinceStart": 5.820038318634033
    },
    {
      "aimPoint": {
        "x": 318.5579528808594,
        "y": 318.13299560546875
      },
      "direction": 0.7789599299430847,
      "dropPoint": {
        "x": 317.15411376953125,
        "y": 316.7323303222656
      },
      "position": {
        "x": 292.65057373046875,
        "y": 292.55706787109375
      },
      "predictedTarget": {
        "x": 343.0693359375,
        "y": 342.3003234863281
      },
      "state": 4,
      "targetIndex": 4,
      "timeSecSinceStart": 5.920040607452393
    },
    {
      "aimPoint": {
        "x": 319.4200439453125,
        "y": 318.96783447265625
      },
      "direction": 0.7786540985107422,
      "dropPoint": {
        "x": 317.16912841796875,
        "y": 316.7354431152344
      },
      "position": {
        "x": 293.50482177734375,
        "y": 293.39984130859375
      },
      "predictedTarget": {
        "x": 343.0906982421875,
        "y": 342.2969970703125
      },
      "state": 4,
      "targetIndex": 4,
      "timeSecSinceStart": 6.00004243850708
    },
    {
      "aimPoint": {
        "x": 320.4945068359375,
        "y": 320.0145568847656
      },
      "direction": 0.7784050107002258,
      "dropPoint": {
        "x": 317.1877136230469,
        "y": 316.7395324707031
      },
      "position": {
        "x": 294.57293701171875,
        "y": 294.4530029296875
      },
      "predictedTarget": {
        "x": 343.1174011230469,
        "y": 342.2928466796875
      },
      "state": 4,
      "targetIndex": 4,
      "timeSecSinceStart": 6.1000447273254395
    },
    {
      "aimPoint": {
        "x": 321.35736083984375,
        "y": 320.8486022949219
      },
      "direction": 0.7780877351760864,
      "dropPoint": {
        "x": 317.2024841308594,
        "y": 316.742919921875
      },
      "position": {
        "x": 295.5345153808594,
        "y": 295.40057373046875
      },
      "predictedTarget": {
        "x": 343.1387939453125,
        "y": 342.2895202636719
      },
      "state": 4,
      "targetIndex": 4,
      "timeSecSinceStart": 6.190046787261963
    },
    {
      "aimPoint": {
        "x": 322.3258056640625,
        "y": 321.7892150878906
      },
      "direction": 0.7778286337852478,
      "dropPoint": {
        "x": 317.21893310546875,
        "y": 316.74688720703125
      },
      "position": {
        "x": 296.3894958496094,
        "y": 296.24261474609375
      },
      "predictedTarget": {
        "x": 343.1628112792969,
        "y": 342.2857971191406
      },
      "state": 4,
      "targetIndex": 4,
      "timeSecSinceStart": 6.27004861831665
    },
    {
      "aimPoint": {
        "x": 323.1885986328125,
        "y": 322.6233215332031
      },
      "direction": 0.7775319218635559,
      "dropPoint": {
        "x": 317.23345947265625,
        "y": 316.75054931640625
      },
      "position": {
        "x": 297.2447204589844,
        "y": 297.08441162109375
      },
      "predictedTarget": {
        "x": 343.1842041015625,
        "y": 342.282470703125
      },
      "state": 4,
      "targetIndex": 4,
      "timeSecSinceStart": 6.350050449371338
    },
    {
      "aimPoint": {
        "x": 323.9440002441406,
        "y": 323.3526916503906
      },
      "direction": 0.7772631049156189,
      "dropPoint": {
        "x": 317.2460632324219,
        "y": 316.7538146972656
      },
      "position": {
        "x": 298.1001892089844,
        "y": 297.92596435546875
      },
      "predictedTarget": {
        "x": 343.202880859375,
        "y": 342.2795715332031
      },
      "state": 4,
      "targetIndex": 4,
      "timeSecSinceStart": 6.430052280426025
    },
    {
      "aimPoint": {
        "x": 324.9127197265625,
        "y": 324.29302978515625
      },
      "direction": 0.777025043964386,
      "dropPoint": {
        "x": 317.2621154785156,
        "y": 316.7582092285156
      },
      "position": {
        "x": 298.9559020996094,
        "y": 298.76727294921875
      },
      "predictedTarget": {
        "x": 343.2269287109375,
        "y": 342.27581787109375
      },
      "state": 4,
      "targetIndex": 4,
      "timeSecSinceStart": 6.510054111480713
    },
    {
      "aimPoint": {
        "x": 325.669677734375,
        "y": 325.02081298828125
      },
      "direction": 0.7767120599746704,
      "dropPoint": {
        "x": 317.2745056152344,
        "y": 316.76171875
      },
      "position": {
        "x": 299.8118591308594,
        "y": 299.60833740234375
      },
      "predictedTarget": {
        "x": 343.2456359863281,
        "y": 342.2729187011719
      },
      "state": 4,
      "targetIndex": 4,
      "timeSecSinceStart": 6.5900559425354
    },
    {
      "aimPoint": {
        "x": 326.6389465332031,
        "y": 325.9603576660156
      },
      "direction": 0.7764648795127869,
      "dropPoint": {
        "x": 317.2901916503906,
        "y": 316.7664794921875
      },
      "position": {
        "x": 300.6678161621094,
        "y": 300.44915771484375
      },
      "predictedTarget": {
        "x": 343.2696533203125,
        "y": 342.2691650390625
      },
      "state": 4,
      "targetIndex": 4,
      "timeSecSinceStart": 6.670057773590088
    },
    {
      "aimPoint": {
        "x": 327.61077880859375,
        "y": 326.8974914550781
      },
      "direction": 0.7761374115943909,
      "dropPoint": {
        "x": 317.3057556152344,
        "y": 316.7713623046875
      },
      "position": {
        "x": 301.6313171386719,
        "y": 301.3948059082031
      },
      "predictedTarget": {
        "x": 343.293701171875,
        "y": 342.26544189453125
      },
      "state": 4,
      "targetIndex": 4,
      "timeSecSinceStart": 6.760059833526611
    },
    {
      "aimPoint": {
        "x": 328.4759521484375,
        "y": 327.7292175292969
      },
      "direction": 0.7758053541183472,
      "dropPoint": {
        "x": 317.3194274902344,
        "y": 316.7759094238281
      },
      "position": {
        "x": 302.4880065917969,
        "y": 302.2351379394531
      },
      "predictedTarget": {
        "x": 343.3150634765625,
        "y": 342.2621154785156
      },
      "state": 4,
      "targetIndex": 4,
      "timeSecSinceStart": 6.840061664581299
    },
    {
      "aimPoint": {
        "x": 329.03961181640625,
        "y": 328.2665100097656
      },
      "direction": 0.7755031585693359,
      "dropPoint": {
        "x": 317.3281555175781,
        "y": 316.7789611816406
      },
      "position": {
        "x": 303.4520568847656,
        "y": 303.18023681640625
      },
      "predictedTarget": {
        "x": 343.32891845703125,
        "y": 342.25994873046875
      },
      "state": 4,
      "targetIndex": 4,
      "timeSecSinceStart": 6.930063724517822
    },
    {
      "aimPoint": {
        "x": 329.0447082519531,
        "y": 328.2613220214844
      },
      "direction": 0.7753024697303772,
      "dropPoint": {
        "x": 317.3281555175781,
        "y": 316.7789611816406
      },
      "position": {
        "x": 304.3089904785156,
        "y": 304.02008056640625
      },
      "predictedTarget": {
        "x": 343.32891845703125,
        "y": 342.25994873046875
      },
      "state": 4,
      "targetIndex": 4,
      "timeSecSinceStart": 7.01006555557251
    },
    {
      "aimPoint": {
        "x": 329.0447082519531,
        "y": 328.2613525390625
      },
      "direction": 0.7753019332885742,
      "dropPoint": {
        "x": 317.328125,
        "y": 316.77899169921875
      },
      "position": {
        "x": 305.1659240722656,
        "y": 304.85992431640625
      },
      "predictedTarget": {
        "x": 343.32891845703125,
        "y": 342.25994873046875
      },
      "state": 4,
      "targetIndex": 4,
      "timeSecSinceStart": 7.090067386627197
    },
    {
      "aimPoint": {
        "x": 329.0447082519531,
        "y": 328.2613525390625
      },
      "direction": 0.7753013968467712,
      "dropPoint": {
        "x": 317.328125,
        "y": 316.77899169921875
      },
      "position": {
        "x": 306.1299743652344,
        "y": 305.80474853515625
      },
      "predictedTarget": {
        "x": 343.32891845703125,
        "y": 342.25994873046875
      },
      "state": 4,
      "targetIndex": 4,
      "timeSecSinceStart": 7.180069446563721
    },
    {
      "aimPoint": {
        "x": 329.044677734375,
        "y": 328.2613525390625
      },
      "direction": 0.7753007411956787,
      "dropPoint": {
        "x": 317.3280944824219,
        "y": 316.7790222167969
      },
      "position": {
        "x": 306.9869079589844,
        "y": 306.64459228515625
      },
      "predictedTarget": {
        "x": 343.32891845703125,
        "y": 342.25994873046875
      },
      "state": 4,
      "targetIndex": 4,
      "timeSecSinceStart": 7.260071277618408
    },
    {
      "aimPoint": {
        "x": 329.044677734375,
        "y": 328.2613525390625
      },
      "direction": 0.7753000855445862,
      "dropPoint": {
        "x": 317.3280944824219,
        "y": 316.7790222167969
      },
      "position": {
        "x": 307.9509582519531,
        "y": 307.58941650390625
      },
      "predictedTarget": {
        "x": 343.32891845703125,
        "y": 342.25994873046875
      },
      "state": 4,
      "targetIndex": 4,
      "timeSecSinceStart": 7.350073337554932
    },
    {
      "aimPoint": {
        "x": 329.0446472167969,
        "y": 328.2613830566406
      },
      "direction": 0.7752993702888489,
      "dropPoint": {
        "x": 317.32806396484375,
        "y": 316.779052734375
      },
      "position": {
        "x": 309.0221252441406,
        "y": 308.63922119140625
      },
      "predictedTarget": {
        "x": 343.32891845703125,
        "y": 342.25994873046875
      },
      "state": 4,
      "targetIndex": 4,
      "timeSecSinceStart": 7.450075626373291
    },
    {
      "aimPoint": {
        "x": 329.0446472167969,
        "y": 328.2613830566406
      },
      "direction": 0.775298535823822,
      "dropPoint": {
        "x": 317.3280334472656,
        "y": 316.779052734375
      },
      "position": {
        "x": 309.8790588378906,
        "y": 309.47906494140625
      },
      "predictedTarget": {
        "x": 343.32891845703125,
        "y": 342.25994873046875
      },
      "state": 4,
      "targetIndex": 4,
      "timeSecSinceStart": 7.5300774574279785
    },
    {
      "aimPoint": {
        "x": 329.0446472167969,
        "y": 328.2613830566406
      },
      "direction": 0.7752978205680847,
      "dropPoint": {
        "x": 317.3280334472656,
        "y": 316.7790832519531
      },
      "position": {
        "x": 310.8431091308594,
        "y": 310.42388916015625
      },
      "predictedTarget": {
        "x": 343.32891845703125,
        "y": 342.25994873046875
      },
      "state": 4,
      "targetIndex": 4,
      "timeSecSinceStart": 7.620079517364502
    },
    {
      "aimPoint": {
        "x": 327.5194396972656,
        "y": 326.1573486328125
      },
      "direction": 0.7752969861030579,
      "dropPoint": {
        "x": 315.3862609863281,
        "y": 315.08782958984375
      },
      "position": {
        "x": 311.80743408203125,
        "y": 311.36871337890625
      },
      "predictedTarget": {
        "x": 340.62890625,
        "y": 341.3200378417969
      },
      "state": 4,
      "targetIndex": 4,
      "timeSecSinceStart": 7.710081577301025
    },
    {
      "aimPoint": {
        "x": 326.7672119140625,
        "y": 326.90289306640625
      },
      "direction": 0.8046198487281799,
      "dropPoint": {
        "x": 315.39013671875,
        "y": 315.0840759277344
      },
      "position": {
        "x": 312.8517761230469,
        "y": 312.4454345703125
      },
      "predictedTarget": {
        "x": 340.62890625,
        "y": 341.3200378417969
      },
      "state": 4,
      "targetIndex": 4,
      "timeSecSinceStart": 7.810083866119385
    },
    {
      "aimPoint": {
        "x": 326.7634582519531,
        "y": 326.9065246582031
      },
      "direction": 0.8047680258750916,
      "dropPoint": {
        "x": 315.3902282714844,
        "y": 315.0840148925781
      },
      "position": {
        "x": 313.7878112792969,
        "y": 313.41827392578125
      },
      "predictedTarget": {
        "x": 340.62890625,
        "y": 341.3200378417969
      },
      "state": 4,
      "targetIndex": 4,
      "timeSecSinceStart": 7.900085926055908
    },
    {
      "aimPoint": {
        "x": 326.7635192871094,
        "y": 326.9064636230469
      },
      "direction": 0.8047712445259094,
      "dropPoint": {
        "x": 315.39031982421875,
        "y": 315.08392333984375
      },
      "position": {
        "x": 314.7238464355469,
        "y": 314.39111328125
      },
      "predictedTarget": {
        "x": 340.62890625,
        "y": 341.3200378417969
      },
      "state": 4,
      "targetIndex": 4,
      "timeSecSinceStart": 7.990087985992432
    }
  ],
  "totalSteps": 95
}